Workbook

Sheet 0_Теория
A1: Занятие 8. Фильтрация, сортировка и вычисляемые столбцы
A3: Тема | B3: Как фильтровать строки, сортировать таблицу и создавать новые столбцы в Excel и Python.
A4: Зачем это нужно | B4: Фильтрация помогает быстро находить нужные строки, сортировка — видеть приоритеты, а новые столбцы — делать расчёты по данным.
A5: Ключевые методы Python | B5: pd.read_excel(), df[условие], &, sort_values(), df["new_column"] = ..., sum().
A6: Ключевые действия в Excel | B6: Автофильтр, IF+AND для проверки условий, сортировка по столбцу, формулы для расчёта revenue.
A7: Мини-проект урока | B7: Посчитать выручку по заказам, найти крупные заказы и отсортировать их по убыванию.

Sheet sales_data
A1: Лист sales_data — исходные данные для ноутбука
A2: order_id | B2: date | C2: day | D2: month | E2: manager | F2: city | G2: region | H2: category | I2: product | J2: client_type | K2: quantity | L2: price_per_unit | M2: revenue | N2: channel | O2: status
A3: 85 | B3: 45881 | C3: 12 | D3: Август | E3: Владимир | F3: Уфа | G3: Приволжский | H3: Аксессуары | I3: Screen Protector | J3: Опт | K3: 20 | L3: 800 | M3: 16000 | N3: Интернет-магазин | O3: В пути
A4: 225 | B4: 45697 | C4: 9 | D4: Февраль | E4: Сергей | F4: Казань | G4: Приволжский | H4: Аксессуары | I4: Screen Protector | J4: Опт | K4: 25 | L4: 800 | M4: 20000 | N4: Офлайн-точка | O4: Доставлен
A5: 332 | B5: 45941 | C5: 11 | D5: Октябрь | E5: Борис | F5: Омск | G5: Сибирский | H5: Аксессуары | I5: Screen Protector | J5: Опт | K5: 5 | L5: 800 | M5: 4000 | N5: Офлайн-точка | O5: В пути
A6: 430 | B6: 45746 | C6: 30 | D6: Март | E6: Светлана | F6: Новосибирск | G6: Сибирский | H6: Аксессуары | I6: Screen Protector | J6: Опт | K6: 42 | L6: 800 | M6: 33600 | N6: Интернет-магазин | O6: Отменён
A7: 459 | B7: 45856 | C7: 18 | D7: Июль | E7: Мария | F7: Нижний Новгород | G7: Приволжский | H7: Аксессуары | I7: Screen Protector | J7: Опт | K7: 38 | L7: 800 | M7: 30400 | N7: Офлайн-точка | O7: Доставлен
A8: 570 | B8: 45766 | C8: 19 | D8: Апрель | E8: Ксения | F8: Москва | G8: Центральный | H8: Аксессуары | I8: Screen Protector | J8: Опт | K8: 46 | L8: 800 | M8: 36800 | N8: Интернет-магазин | O8: В пути
A9: 639 | B9: 45901 | C9: 1 | D9: Сентябрь | E9: Павел | F9: Пермь | G9: Приволжский | H9: Аксессуары | I9: Screen Protector | J9: Опт | K9: 13 | L9: 800 | M9: 10400 | N9: Интернет-магазин | O9: Отменён
A10: 665 | B10: 45809 | C10: 1 | D10: Июнь | E10: Владимир | F10: Екатеринбург | G10: Уральский | H10: Аксессуары | I10: Screen Protector | J10: Опт | K10: 5 | L10: 800 | M10: 4000 | N10: Офлайн-точка | O10: Отменён
A11: 746 | B11: 45979 | C11: 18 | D11: Ноябрь | E11: Павел | F11: Воронеж | G11: Центральный | H11: Аксессуары | I11: Screen Protector | J11: Опт | K11: 31 | L11: 800 | M11: 24800 | N11: Интернет-магазин | O11: Отменён
A12: 1035 | B12: 45812 | C12: 4 | D12: Июнь | E12: Борис | F12: Москва | G12: Центральный | H12: Аксессуары | I12: Screen Protector | J12: Опт | K12: 13 | L12: 800 | M12: 10400 | N12: Офлайн-точка | O12: Доставлен
A13: 1562 | B13: 45696 | C13: 8 | D13: Февраль | E13: Игорь | F13: Казань | G13: Приволжский | H13: Аксессуары | I13: Screen Protector | J13: Опт | K13: 34 | L13: 800 | M13: 27200 | N13: Интернет-магазин | O13: Отменён
A14: 1720 | B14: 45786 | C14: 9 | D14: Май | E14: Наталья | F14: Нижний Новгород | G14: Приволжский | H14: Аксессуары | I14: Screen Protector | J14: Опт | K14: 45 | L14: 800 | M14: 36000 | N14: Интернет-магазин | O14: В пути
... A5002: 180 | B5002: 45837 | C5002: 29 | D5002: Июнь | E5002: Алексей | F5002: Пермь | G5002: Приволжский | H5002: Серверы | I5002: Server Blade | J5002: Розница | K5002: 2 | L5002: 227200 | M5002: 454400 | N5002: Интернет-магазин | O5002: В пути

Sheet 1_Обзор
A1: Шаг 1. Загружаем таблицу и смотрим на её структуру
A3: Показатель | B3: Значение | D3: order_id | E3: month | F3: city | G3: category | H3: product | I3: quantity | J3: price | K3: manager | L3: channel
A4: Количество строк | B4: =COUNTA(sales_data!A3:A5002) -> 5000 | D4: =sales_data!A3 -> 85 | E4: =sales_data!D3 -> Август | F4: =sales_data!F3 -> Уфа | G4: =sales_data!H3 -> Аксессуары | H4: =sales_data!I3 -> Screen Protector | I4: =sales_data!K3 -> 20 | J4: =sales_data!L3 -> 800 | K4: =sales_data!E3 -> Владимир | L4: =sales_data!N3 -> Интернет-магазин
A5: Количество столбцов | B5: =COUNTA(sales_data!A2:'sales_data'!O2) -> 15 | D5: =sales_data!A4 -> 225 | E5: =sales_data!D4 -> Февраль | F5: =sales_data!F4 -> Казань | G5: =sales_data!H4 -> Аксессуары | H5: =sales_data!I4 -> Screen Protector | I5: =sales_data!K4 -> 25 | J5: =sales_data!L4 -> 800 | K5: =sales_data!E4 -> Сергей | L5: =sales_data!N4 -> Офлайн-точка
A6: Уникальных категорий | B6: =COUNTA(_xlfn.UNIQUE(sales_data!H3:H5002)) -> 6 | D6: =sales_data!A5 -> 332 | E6: =sales_data!D5 -> Октябрь | F6: =sales_data!F5 -> Омск | G6: =sales_data!H5 -> Аксессуары | H6: =sales_data!I5 -> Screen Protector | I6: =sales_data!K5 -> 5 | J6: =sales_data!L5 -> 800 | K6: =sales_data!E5 -> Борис | L6: =sales_data!N5 -> Офлайн-точка
A7: Есть ли онлайн-заказы? | B7: =IF(COUNTIF(sales_data!N3:N5002,"Интернет-магазин")>0,"Да","Нет") -> Да | D7: =sales_data!A6 -> 430 | E7: =sales_data!D6 -> Март | F7: =sales_data!F6 -> Новосибирск | G7: =sales_data!H6 -> Аксессуары | H7: =sales_data!I6 -> Screen Protector | I7: =sales_data!K6 -> 42 | J7: =sales_data!L6 -> 800 | K7: =sales_data!E6 -> Светлана | L7: =sales_data!N6 -> Интернет-магазин

Sheet 2_Фильтр_1
A1: Шаг 2. Фильтрация по одному условию: category == "Ноутбуки"
A3: order_id | B3: client | C3: city | D3: category | E3: product | F3: quantity | G3: price | H3: manager | I3: channel | J3: flag_ноутбуки | L3: order_id | M3: date | N3: day | O3: month | P3: manager | Q3: city | R3: region | S3: category | T3: product | U3: client_type | V3: quantity | W3: price_per_unit | X3: revenue | Y3: channel | Z3: status
A4: 201 | B4: ООО Альфа | C4: Москва | D4: Ноутбуки | E4: Notebook Air | F4: 2 | G4: 55000 | H4: Анна | I4: Онлайн | J4: =IF(D4="Ноутбуки","Да","Нет") -> Да | L4: =sales_data!A6 -> 430 | M4: =sales_data!B6 -> 45746 | N4: =sales_data!C6 -> 30 | O4: =sales_data!D6 -> Март | P4: =sales_data!E6 -> Светлана | Q4: =sales_data!F6 -> Новосибирск | R4: =sales_data!G6 -> Сибирский | S4: =sales_data!H6 -> Аксессуары | ... Z4: =sales_data!O6 -> Отменён
A5: 202 | B5: ООО Бета | C5: Санкт-Петербург | D5: Мониторы | E5: Monitor 27 | F5: 1 | G5: 23000 | H5: Борис | I5: Офлайн | J5: =IF(D5="Ноутбуки","Да","Нет") -> Нет | L5: =sales_data!A7 -> 459 | M5: =sales_data!B7 -> 45856 | N5: =sales_data!C7 -> 18 | O5: =sales_data!D7 -> Июль | P5: =sales_data!E7 -> Мария | Q5: =sales_data!F7 -> Нижний Новгород | R5: =sales_data!G7 -> Приволжский | S5: =sales_data!H7 -> Аксессуары | ... Z5: =sales_data!O7 -> Доставлен
A6: 203 | B6: ИП Гамма | C6: Москва | D6: Ноутбуки | E6: Notebook Pro | F6: 3 | G6: 72000 | H6: Анна | I6: Онлайн | J6: =IF(D6="Ноутбуки","Да","Нет") -> Да | L6: =sales_data!A8 -> 570 | M6: =sales_data!B8 -> 45766 | N6: =sales_data!C8 -> 19 | O6: =sales_data!D8 -> Апрель | P6: =sales_data!E8 -> Ксения | Q6: =sales_data!F8 -> Москва | R6: =sales_data!G8 -> Центральный | S6: =sales_data!H8 -> Аксессуары | ... Z6: =sales_data!O8 -> В пути
A7: 204 | B7: ООО Дельта | C7: Казань | D7: Периферия | E7: Mouse Pro | F7: 5 | G7: 2500 | H7: Виктор | I7: Маркетплейс | J7: =IF(D7="Ноутбуки","Да","Нет") -> Нет | L7: =sales_data!A10 -> 665 | M7: =sales_data!B10 -> 45809 | N7: =sales_data!C10 -> 1 | O7: =sales_data!D10 -> Июнь | P7: =sales_data!E10 -> Владимир | Q7: =sales_data!F10 -> Екатеринбург | R7: =sales_data!G10 -> Уральский | S7: =sales_data!H10 -> Аксессуары | ... Z7: =sales_data!O10 -> Отменён
A8: 205 | B8: ООО Эпсилон | C8: Москва | D8: Мониторы | E8: Monitor 24 | F8: 2 | G8: 18000 | H8: Анна | I8: Онлайн | J8: =IF(D8="Ноутбуки","Да","Нет") -> Нет | L8: =sales_data!A19 -> 2086 | M8: =sales_data!B19 -> 45742 | N8: =sales_data!C19 -> 26 | O8: =sales_data!D19 -> Март | P8: =sales_data!E19 -> Игорь | Q8: =sales_data!F19 -> Казань | R8: =sales_data!G19 -> Приволжский | S8: =sales_data!H19 -> Аксессуары | ... Z8: =sales_data!O19 -> Доставлен
A9: 206 | B9: ИП Жасмин | C9: Екатеринбург | D9: Ноутбуки | E9: Notebook Lite | F9: 1 | G9: 49000 | H9: Борис | I9: Офлайн | J9: =IF(D9="Ноутбуки","Да","Нет") -> Да | L9: =sales_data!A28 -> 3062 | M9: =sales_data!B28 -> 45664 | N9: =sales_data!C28 -> 7 | O9: =sales_data!D28 -> Январь | P9: =sales_data!E28 -> Татьяна | Q9: =sales_data!F28 -> Воронеж | R9: =sales_data!G28 -> Центральный | S9: =sales_data!H28 -> Аксессуары | ... Z9: =sales_data!O28 -> В пути
A10: 207 | B10: ООО Зета | C10: Москва | D10: Периферия | E10: Keyboard X | F10: 4 | G10: 4000 | H10: Виктор | I10: Онлайн | J10: =IF(D10="Ноутбуки","Да","Нет") -> Нет | L10: =sales_data!A33 -> 3945 | M10: =sales_data!B33 -> 45787 | N10: =sales_data!C33 -> 10 | O10: =sales_data!D33 -> Май | P10: =sales_data!E33 -> Мария | Q10: =sales_data!F33 -> Воронеж | R10: =sales_data!G33 -> Центральный | S10: =sales_data!H33 -> Аксессуары | ... Z10: =sales_data!O33 -> В пути
A11: 208 | B11: ООО Ита | C11: Новосибирск | D11: Ноутбуки | E11: Notebook Air | F11: 2 | G11: 55000 | H11: Анна | I11: Маркетплейс | J11: =IF(D11="Ноутбуки","Да","Нет") -> Да | L11: =sales_data!A36 -> 4279 | M11: =sales_data!B36 -> 45810 | N11: =sales_data!C36 -> 2 | O11: =sales_data!D36 -> Июнь | P11: =sales_data!E36 -> Игорь | Q11: =sales_data!F36 -> Омск | R11: =sales_data!G36 -> Сибирский | S11: =sales_data!H36 -> Аксессуары | ... Z11: =sales_data!O36 -> В пути
A12: 209 | B12: ООО Каппа | C12: Москва | D12: Ноутбуки | E12: Notebook Start | F12: 1 | G12: 43000 | H12: Борис | I12: Офлайн | J12: =IF(D12="Ноутбуки","Да","Нет") -> Да | L12: =sales_data!A39 -> 500 | M12: =sales_data!B39 -> 45996 | N12: =sales_data!C39 -> 5 | O12: =sales_data!D39 -> Декабрь | P12: =sales_data!E39 -> Борис | Q12: =sales_data!F39 -> Ростов-на-Дону | R12: =sales_data!G39 -> Южный | S12: =sales_data!H39 -> Аксессуары | ... Z12: =sales_data!O39 -> Отменён
L13: =sales_data!A52 -> 1518 | M13: =sales_data!B52 -> 45836 | N13: =sales_data!C52 -> 28 | O13: =sales_data!D52 -> Июнь | P13: =sales_data!E52 -> Ксения | Q13: =sales_data!F52 -> Москва | R13: =sales_data!G52 -> Центральный | S13: =sales_data!H52 -> Аксессуары | ... Z13: =sales_data!O52 -> Доставлен
L14: =sales_data!A57 -> 1911 | M14: =sales_data!B57 -> 45741 | N14: =sales_data!C57 -> 25 | O14: =sales_data!D57 -> Март | P14: =sales_data!E57 -> Ольга | Q14: =sales_data!F57 -> Ростов-на-Дону | R14: =sales_data!G57 -> Южный | S14: =sales_data!H57 -> Аксессуары | ... Z14: =sales_data!O57 -> Доставлен
L15: =sales_data!A64 -> 2460 | M15: =sales_data!B64 -> 45698 | N15: =sales_data!C64 -> 10 | O15: =sales_data!D64 -> Февраль | P15: =sales_data!E64 -> Светлана | Q15: =sales_data!F64 -> Омск | R15: =sales_data!G64 -> Сибирский | S15: =sales_data!H64 -> Аксессуары | ... Z15: =sales_data!O64 -> В пути
L16: =sales_data!A72 -> 2688 | M16: =sales_data!B72 -> 45791 | N16: =sales_data!C72 -> 14 | O16: =sales_data!D72 -> Май | P16: =sales_data!E72 -> Алексей | Q16: =sales_data!F72 -> Краснодар | R16: =sales_data!G72 -> Южный | S16: =sales_data!H72 -> Аксессуары | ... Z16: =sales_data!O72 -> В пути
L17: =sales_data!A80 -> 3183 | M17: =sales_data!B80 -> 45854 | N17: =sales_data!C80 -> 16 | O17: =sales_data!D80 -> Июль | P17: =sales_data!E80 -> Борис | Q17: =sales_data!F80 -> Уфа | R17: =sales_data!G80 -> Приволжский | S17: =sales_data!H80 -> Аксессуары | ... Z17: =sales_data!O80 -> В пути
L18: =sales_data!A85 -> 3892 | M18: =sales_data!B85 -> 45812 | N18: =sales_data!C85 -> 4 | O18: =sales_data!D85 -> Июнь | P18: =sales_data!E85 -> Наталья | Q18: =sales_data!F85 -> Санкт-Петербург | R18: =sales_data!G85 -> Северо-Западный | S18: =sales_data!H85 -> Аксессуары | ... Z18: =sales_data!O85 -> В пути
L19: =sales_data!A90 -> 4115 | M19: =sales_data!B90 -> 45966 | N19: =sales_data!C90 -> 5 | O19: =sales_data!D90 -> Ноябрь | P19: =sales_data!E90 -> Дмитрий | Q19: =sales_data!F90 -> Челябинск | R19: =sales_data!G90 -> Уральский | S19: =sales_data!H90 -> Аксессуары | ... Z19: =sales_data!O90 -> В пути
L20: =sales_data!A109 -> 246 | M20: =sales_data!B109 -> 45739 | N20: =sales_data!C109 -> 23 | O20: =sales_data!D109 -> Март | P20: =sales_data!E109 -> Владимир | Q20: =sales_data!F109 -> Краснодар | R20: =sales_data!G109 -> Южный | S20: =sales_data!H109 -> Аксессуары | ... Z20: =sales_data!O109 -> Отменён
L21: =sales_data!A117 -> 558 | M21: =sales_data!B117 -> 45858 | N21: =sales_data!C117 -> 20 | O21: =sales_data!D117 -> Июль | P21: =sales_data!E117 -> Наталья | Q21: =sales_data!F117 -> Красноярск | R21: =sales_data!G117 -> Сибирский | S21: =sales_data!H117 -> Аксессуары | ... Z21: =sales_data!O117 -> Доставлен
L22: =sales_data!A125 -> 729 | M22: =sales_data!B125 -> 45725 | N22: =sales_data!C125 -> 9 | O22: =sales_data!D125 -> Март | P22: =sales_data!E125 -> Дмитрий | Q22: =sales_data!F125 -> Москва | R22: =sales_data!G125 -> Центральный | S22: =sales_data!H125 -> Аксессуары | ... Z22: =sales_data!O125 -> В пути
L23: =sales_data!A130 -> 1037 | M23: =sales_data!B130 -> 45672 | N23: =sales_data!C130 -> 15 | O23: =sales_data!D130 -> Январь | P23: =sales_data!E130 -> Ксения | Q23: =sales_data!F130 -> Красноярск | R23: =sales_data!G130 -> Сибирский | S23: =sales_data!H130 -> Аксессуары | ... Z23: =sales_data!O130 -> Отменён
L24: =sales_data!A135 -> 1493 | M24: =sales_data!B135 -> 45949 | N24: =sales_data!C135 -> 19 | O24: =sales_data!D135 -> Октябрь | P24: =sales_data!E135 -> Борис | Q24: =sales_data!F135 -> Казань | R24: =sales_data!G135 -> Приволжский | S24: =sales_data!H135 -> Аксессуары | ... Z24: =sales_data!O135 -> Доставлен
L25: =sales_data!A136 -> 1553 | M25: =sales_data!B136 -> 45682 | N25: =sales_data!C136 -> 25 | O25: =sales_data!D136 -> Январь | P25: =sales_data!E136 -> Сергей | Q25: =sales_data!F136 -> Самара | R25: =sales_data!G136 -> Приволжский | S25: =sales_data!H136 -> Аксессуары | ... Z25: =sales_data!O136 -> В пути
L26: =sales_data!A150 -> 2320 | M26: =sales_data!B150 -> 45778 | N26: =sales_data!C150 -> 1 | O26: =sales_data!D150 -> Май | P26: =sales_data!E150 -> Владимир | Q26: =sales_data!F150 -> Самара | R26: =sales_data!G150 -> Приволжский | S26: =sales_data!H150 -> Аксессуары | ... Z26: =sales_data!O150 -> Доставлен
L27: =sales_data!A158 -> 2770 | M27: =sales_data!B158 -> 45974 | N27: =sales_data!C158 -> 13 | O27: =sales_data!D158 -> Ноябрь | P27: =sales_data!E158 -> Ольга | Q27: =sales_data!F158 -> Нижний Новгород | R27: =sales_data!G158 -> Приволжский | S27: =sales_data!H158 -> Аксессуары | ... Z27: =sales_data!O158 -> В пути
L28: =sales_data!A160 -> 2772 | M28: =sales_data!B160 -> 45944 | N28: =sales_data!C160 -> 14 | O28: =sales_data!D160 -> Октябрь | P28: =sales_data!E160 -> Игорь | Q28: =sales_data!F160 -> Ростов-на-Дону | R28: =sales_data!G160 -> Южный | S28: =sales_data!H160 -> Аксессуары | ... Z28: =sales_data!O160 -> Доставлен
L29: =sales_data!A166 -> 3135 | M29: =sales_data!B166 -> 45926 | N29: =sales_data!C166 -> 26 | O29: =sales_data!D166 -> Сентябрь | P29: =sales_data!E166 -> Светлана | Q29: =sales_data!F166 -> Москва | R29: =sales_data!G166 -> Центральный | S29: =sales_data!H166 -> Аксессуары | ... Z29: =sales_data!O166 -> Доставлен
L30: =sales_data!A169 -> 3434 | M30: =sales_data!B169 -> 45910 | N30: =sales_data!C169 -> 10 | O30: =sales_data!D169 -> Сентябрь | P30: =sales_data!E169 -> Наталья | Q30: =sales_data!F169 -> Краснодар | R30: =sales_data!G169 -> Южный | S30: =sales_data!H169 -> Аксессуары | ... Z30: =sales_data!O169 -> Отменён
L31: =sales_data!A174 -> 3822 | M31: =sales_data!B174 -> 45765 | N31: =sales_data!C174 -> 18 | O31: =sales_data!D174 -> Апрель | P31: =sales_data!E174 -> Анна | Q31: =sales_data!F174 -> Нижний Новгород | R31: =sales_data!G174 -> Приволжский | S31: =sales_data!H174 -> Аксессуары | ... Z31: =sales_data!O174 -> Отменён
L32: =sales_data!A175 -> 3872 | M32: =sales_data!B175 -> 45676 | N32: =sales_data!C175 -> 19 | O32: =sales_data!D175 -> Январь | P32: =sales_data!E175 -> Ольга | Q32: =sales_data!F175 -> Челябинск | R32: =sales_data!G175 -> Уральский | S32: =sales_data!H175 -> Аксессуары | ... Z32: =sales_data!O175 -> Отменён
L33: =sales_data!A181 -> 4331 | M33: =sales_data!B181 -> 45678 | N33: =sales_data!C181 -> 21 | O33: =sales_data!D181 -> Январь | P33: =sales_data!E181 -> Борис | Q33: =sales_data!F181 -> Екатеринбург | R33: =sales_data!G181 -> Уральский | S33: =sales_data!H181 -> Аксессуары | ... Z33: =sales_data!O181 -> Отменён
L34: =sales_data!A187 -> 4448 | M34: =sales_data!B187 -> 45966 | N34: =sales_data!C187 -> 5 | O34: =sales_data!D187 -> Ноябрь | P34: =sales_data!E187 -> Анна | Q34: =sales_data!F187 -> Екатеринбург | R34: =sales_data!G187 -> Уральский | S34: =sales_data!H187 -> Аксессуары | ... Z34: =sales_data!O187 -> Отменён
L35: =sales_data!A197 -> 4708 | M35: =sales_data!B197 -> 45686 | N35: =sales_data!C197 -> 29 | O35: =sales_data!D197 -> Январь | P35: =sales_data!E197 -> Ксения | Q35: =sales_data!F197 -> Челябинск | R35: =sales_data!G197 -> Уральский | S35: =sales_data!H197 -> Аксессуары | ... Z35: =sales_data!O197 -> Отменён
L36: =sales_data!A202 -> 4969 | M36: =sales_data!B202 -> 45844 | N36: =sales_data!C202 -> 6 | O36: =sales_data!D202 -> Июль | P36: =sales_data!E202 -> Анна | Q36: =sales_data!F202 -> Екатеринбург | R36: =sales_data!G202 -> Уральский | S36: =sales_data!H202 -> Аксессуары | ... Z36: =sales_data!O202 -> Отменён
L37: =sales_data!A204 -> 4996 | M37: =sales_data!B204 -> 45818 | N37: =sales_data!C204 -> 10 | O37: =sales_data!D204 -> Июнь | P37: =sales_data!E204 -> Владимир | Q37: =sales_data!F204 -> Омск | R37: =sales_data!G204 -> Сибирский | S37: =sales_data!H204 -> Аксессуары | ... Z37: =sales_data!O204 -> Доставлен
L38: =sales_data!A206 -> 7 | M38: =sales_data!B206 -> 45808 | N38: =sales_data!C206 -> 31 | O38: =sales_data!D206 -> Май | P38: =sales_data!E206 -> Владимир | Q38: =sales_data!F206 -> Ростов-на-Дону | R38: =sales_data!G206 -> Южный | S38: =sales_data!H206 -> Аксессуары | ... Z38: =sales_data!O206 -> Отменён
L39: =sales_data!A225 -> 2078 | M39: =sales_data!B225 -> 46007 | N39: =sales_data!C225 -> 16 | O39: =sales_data!D225 -> Декабрь | P39: =sales_data!E225 -> Владимир | Q39: =sales_data!F225 -> Уфа | R39: =sales_data!G225 -> Приволжский | S39: =sales_data!H225 -> Аксессуары | ... Z39: =sales_data!O225 -> Доставлен
L40: =sales_data!A230 -> 2532 | M40: =sales_data!B230 -> 45877 | N40: =sales_data!C230 -> 8 | O40: =sales_data!D230 -> Август | P40: =sales_data!E230 -> Павел | Q40: =sales_data!F230 -> Новосибирск | R40: =sales_data!G230 -> Сибирский | S40: =sales_data!H230 -> Аксессуары | ... Z40: =sales_data!O230 -> Отменён
L41: =sales_data!A234 -> 3074 | M41: =sales_data!B234 -> 45992 | N41: =sales_data!C234 -> 1 | O41: =sales_data!D234 -> Декабрь | P41: =sales_data!E234 -> Анна | Q41: =sales_data!F234 -> Москва | R41: =sales_data!G234 -> Центральный | S41: =sales_data!H234 -> Аксессуары | ... Z41: =sales_data!O234 -> Отменён
L42: =sales_data!A247 -> 4029 | M42: =sales_data!B247 -> 45862 | N42: =sales_data!C247 -> 24 | O42: =sales_data!D247 -> Июль | P42: =sales_data!E247 -> Сергей | Q42: =sales_data!F247 -> Челябинск | R42: =sales_data!G247 -> Уральский | S42: =sales_data!H247 -> Аксессуары | ... Z42: =sales_data!O247 -> В пути
L43: =sales_data!A270 -> 985 | M43: =sales_data!B270 -> 45918 | N43: =sales_data!C270 -> 18 | O43: =sales_data!D270 -> Сентябрь | P43: =sales_data!E270 -> Владимир | Q43: =sales_data!F270 -> Екатеринбург | R43: =sales_data!G270 -> Уральский | S43: =sales_data!H270 -> Аксессуары | ... Z43: =sales_data!O270 -> Отменён
L44: =sales_data!A278 -> 1506 | M44: =sales_data!B278 -> 45869 | N44: =sales_data!C278 -> 31 | O44: =sales_data!D278 -> Июль | P44: =sales_data!E278 -> Алексей | Q44: =sales_data!F278 -> Красноярск | R44: =sales_data!G278 -> Сибирский | S44: =sales_data!H278 -> Аксессуары | ... Z44: =sales_data!O278 -> Доставлен
L45: =sales_data!A289 -> 2511 | M45: =sales_data!B289 -> 45966 | N45: =sales_data!C289 -> 5 | O45: =sales_data!D289 -> Ноябрь | P45: =sales_data!E289 -> Павел | Q45: =sales_data!F289 -> Краснодар | R45: =sales_data!G289 -> Южный | S45: =sales_data!H289 -> Аксессуары | ... Z45: =sales_data!O289 -> Отменён
L46: =sales_data!A290 -> 2637 | M46: =sales_data!B290 -> 45941 | N46: =sales_data!C290 -> 11 | O46: =sales_data!D290 -> Октябрь | P46: =sales_data!E290 -> Дмитрий | Q46: =sales_data!F290 -> Воронеж | R46: =sales_data!G290 -> Центральный | S46: =sales_data!H290 -> Аксессуары | ... Z46: =sales_data!O290 -> Отменён
L47: =sales_data!A291 -> 2762 | M47: =sales_data!B291 -> 45743 | N47: =sales_data!C291 -> 27 | O47: =sales_data!D291 -> Март | P47: =sales_data!E291 -> Анна | Q47: =sales_data!F291 -> Ростов-на-Дону | R47: =sales_data!G291 -> Южный | S47: =sales_data!H291 -> Аксессуары | ... Z47: =sales_data!O291 -> Доставлен
L48: =sales_data!A304 -> 3848 | M48: =sales_data!B304 -> 45999 | N48: =sales_data!C304 -> 8 | O48: =sales_data!D304 -> Декабрь | P48: =sales_data!E304 -> Наталья | Q48: =sales_data!F304 -> Воронеж | R48: =sales_data!G304 -> Центральный | S48: =sales_data!H304 -> Аксессуары | ... Z48: =sales_data!O304 -> В пути
L49: =sales_data!A317 -> 899 | M49: =sales_data!B317 -> 45944 | N49: =sales_data!C317 -> 14 | O49: =sales_data!D317 -> Октябрь | P49: =sales_data!E317 -> Сергей | Q49: =sales_data!F317 -> Уфа | R49: =sales_data!G317 -> Приволжский | S49: =sales_data!H317 -> Аксессуары | ... Z49: =sales_data!O317 -> Доставлен
L50: =sales_data!A322 -> 2809 | M50: =sales_data!B322 -> 45677 | N50: =sales_data!C322 -> 20 | O50: =sales_data!D322 -> Январь | P50: =sales_data!E322 -> Мария | Q50: =sales_data!F322 -> Челябинск | R50: =sales_data!G322 -> Уральский | S50: =sales_data!H322 -> Аксессуары | ... Z50: =sales_data!O322 -> В пути
L51: =sales_data!A324 -> 3096 | M51: =sales_data!B324 -> 45955 | N51: =sales_data!C324 -> 25 | O51: =sales_data!D324 -> Октябрь | P51: =sales_data!E324 -> Светлана | Q51: =sales_data!F324 -> Красноярск | R51: =sales_data!G324 -> Сибирский | S51: =sales_data!H324 -> Аксессуары | ... Z51: =sales_data!O324 -> В пути
L52: =sales_data!A347 -> 3212 | M52: =sales_data!B347 -> 46007 | N52: =sales_data!C347 -> 16 | O52: =sales_data!D347 -> Декабрь | P52: =sales_data!E347 -> Светлана | Q52: =sales_data!F347 -> Новосибирск | R52: =sales_data!G347 -> Сибирский | S52: =sales_data!H347 -> Аксессуары | ... Z52: =sales_data!O347 -> Доставлен
L53: =sales_data!A349 -> 4396 | M53: =sales_data!B349 -> 46000 | N53: =sales_data!C349 -> 9 | O53: =sales_data!D349 -> Декабрь | P53: =sales_data!E349 -> Павел | Q53: =sales_data!F349 -> Екатеринбург | R53: =sales_data!G349 -> Уральский | S53: =sales_data!H349 -> Аксессуары | ... Z53: =sales_data!O349 -> В пути
L54: =sales_data!A351 -> 4458 | M54: =sales_data!B351 -> 45793 | N54: =sales_data!C351 -> 16 | O54: =sales_data!D351 -> Май | P54: =sales_data!E351 -> Игорь | Q54: =sales_data!F351 -> Москва | R54: =sales_data!G351 -> Центральный | S54: =sales_data!H351 -> Аксессуары | ... Z54: =sales_data!O351 -> Отменён
L55: =sales_data!A356 -> 515 | M55: =sales_data!B356 -> 45987 | N55: =sales_data!C356 -> 26 | O55: =sales_data!D356 -> Ноябрь | P55: =sales_data!E356 -> Ксения | Q55: =sales_data!F356 -> Казань | R55: =sales_data!G356 -> Приволжский | S55: =sales_data!H356 -> Аксессуары | ... Z55: =sales_data!O356 -> В пути
L56: =sales_data!A365 -> 1447 | M56: =sales_data!B365 -> 45912 | N56: =sales_data!C365 -> 12 | O56: =sales_data!D365 -> Сентябрь | P56: =sales_data!E365 -> Анна | Q56: =sales_data!F365 -> Новосибирск | R56: =sales_data!G365 -> Сибирский | S56: =sales_data!H365 -> Аксессуары | ... Z56: =sales_data!O365 -> Доставлен
L57: =sales_data!A373 -> 2288 | M57: =sales_data!B373 -> 45950 | N57: =sales_data!C373 -> 20 | O57: =sales_data!D373 -> Октябрь | P57: =sales_data!E373 -> Светлана | Q57: =sales_data!F373 -> Краснодар | R57: =sales_data!G373 -> Южный | S57: =sales_data!H373 -> Аксессуары | ... Z57: =sales_data!O373 -> Отменён
L58: =sales_data!A374 -> 2294 | M58: =sales_data!B374 -> 45749 | N58: =sales_data!C374 -> 2 | O58: =sales_data!D374 -> Апрель | P58: =sales_data!E374 -> Дмитрий | Q58: =sales_data!F374 -> Воронеж | R58: =sales_data!G374 -> Центральный | S58: =sales_data!H374 -> Аксессуары | ... Z58: =sales_data!O374 -> Доставлен
L59: =sales_data!A379 -> 3171 | M59: =sales_data!B379 -> 45686 | N59: =sales_data!C379 -> 29 | O59: =sales_data!D379 -> Январь | P59: =sales_data!E379 -> Ксения | Q59: =sales_data!F379 -> Новосибирск | R59: =sales_data!G379 -> Сибирский | S59: =sales_data!H379 -> Аксессуары | ... Z59: =sales_data!O379 -> Отменён
L60: =sales_data!A383 -> 3935 | M60: =sales_data!B383 -> 45938 | N60: =sales_data!C383 -> 8 | O60: =sales_data!D383 -> Октябрь | P60: =sales_data!E383 -> Павел | Q60: =sales_data!F383 -> Москва | R60: =sales_data!G383 -> Центральный | S60: =sales_data!H383 -> Аксессуары | ... Z60: =sales_data!O383 -> Отменён
L61: =sales_data!A389 -> 4505 | M61: =sales_data!B389 -> 45862 | N61: =sales_data!C389 -> 24 | O61: =sales_data!D389 -> Июль | P61: =sales_data!E389 -> Ксения | Q61: =sales_data!F389 -> Самара | R61: =sales_data!G389 -> Приволжский | S61: =sales_data!H389 -> Аксессуары | ... Z61: =sales_data!O389 -> Доставлен
L62: =sales_data!A390 -> 4666 | M62: =sales_data!B390 -> 45743 | N62: =sales_data!C390 -> 27 | O62: =sales_data!D390 -> Март | P62: =sales_data!E390 -> Наталья | Q62: =sales_data!F390 -> Челябинск | R62: =sales_data!G390 -> Уральский | S62: =sales_data!H390 -> Аксессуары | ... Z62: =sales_data!O390 -> Отменён
L63: =sales_data!A392 -> 106 | M63: =sales_data!B392 -> 45864 | N63: =sales_data!C392 -> 26 | O63: =sales_data!D392 -> Июль | P63: =sales_data!E392 -> Елена | Q63: =sales_data!F392 -> Самара | R63: =sales_data!G392 -> Приволжский | S63: =sales_data!H392 -> Аксессуары | ... Z63: =sales_data!O392 -> В пути
L64: =sales_data!A397 -> 690 | M64: =sales_data!B397 -> 45950 | N64: =sales_data!C397 -> 20 | O64: =sales_data!D397 -> Октябрь | P64: =sales_data!E397 -> Алексей | Q64: =sales_data!F397 -> Москва | R64: =sales_data!G397 -> Центральный | S64: =sales_data!H397 -> Аксессуары | ... Z64: =sales_data!O397 -> Отменён
L65: =sales_data!A402 -> 1164 | M65: =sales_data!B402 -> 45691 | N65: =sales_data!C402 -> 3 | O65: =sales_data!D402 -> Февраль | P65: =sales_data!E402 -> Татьяна | Q65: =sales_data!F402 -> Пермь | R65: =sales_data!G402 -> Приволжский | S65: =sales_data!H402 -> Периферия | ... Z65: =sales_data!O402 -> Доставлен
L66: =sales_data!A405 -> 1470 | M66: =sales_data!B405 -> 45900 | N66: =sales_data!C405 -> 31 | O66: =sales_data!D405 -> Август | P66: =sales_data!E405 -> Анна | Q66: =sales_data!F405 -> Пермь | R66: =sales_data!G405 -> Приволжский | S66: =sales_data!H405 -> Аксессуары | ... Z66: =sales_data!O405 -> В пути
L67: =sales_data!A411 -> 2130 | M67: =sales_data!B411 -> 45820 | N67: =sales_data!C411 -> 12 | O67: =sales_data!D411 -> Июнь | P67: =sales_data!E411 -> Дмитрий | Q67: =sales_data!F411 -> Екатеринбург | R67: =sales_data!G411 -> Уральский | S67: =sales_data!H411 -> Аксессуары | ... Z67: =sales_data!O411 -> Доставлен
L68: =sales_data!A414 -> 2596 | M68: =sales_data!B414 -> 45662 | N68: =sales_data!C414 -> 5 | O68: =sales_data!D414 -> Январь | P68: =sales_data!E414 -> Елена | Q68: =sales_data!F414 -> Ростов-на-Дону | R68: =sales_data!G414 -> Южный | S68: =sales_data!H414 -> Аксессуары | ... Z68: =sales_data!O414 -> Доставлен
L69: =sales_data!A426 -> 3355 | M69: =sales_data!B426 -> 45716 | N69: =sales_data!C426 -> 28 | O69: =sales_data!D426 -> Февраль | P69: =sales_data!E426 -> Наталья | Q69: =sales_data!F426 -> Новосибирск | R69: =sales_data!G426 -> Сибирский | S69: =sales_data!H426 -> Периферия | ... Z69: =sales_data!O426 -> Отменён
L70: =sales_data!A434 -> 4476 | M70: =sales_data!B434 -> 45961 | N70: =sales_data!C434 -> 31 | O70: =sales_data!D434 -> Октябрь | P70: =sales_data!E434 -> Дмитрий | Q70: =sales_data!F434 -> Пермь | R70: =sales_data!G434 -> Приволжский | S70: =sales_data!H434 -> Аксессуары | ... Z70: =sales_data!O434 -> Отменён
L71: =sales_data!A445 -> 215 | M71: =sales_data!B445 -> 45679 | N71: =sales_data!C445 -> 22 | O71: =sales_data!D445 -> Январь | P71: =sales_data!E445 -> Игорь | Q71: =sales_data!F445 -> Воронеж | R71: =sales_data!G445 -> Центральный | S71: =sales_data!H445 -> Периферия | ... Z71: =sales_data!O445 -> В пути
L72: =sales_data!A447 -> 301 | M72: =sales_data!B447 -> 45850 | N72: =sales_data!C447 -> 12 | O72: =sales_data!D447 -> Июль | P72: =sales_data!E447 -> Светлана | Q72: =sales_data!F447 -> Красноярск | R72: =sales_data!G447 -> Сибирский | S72: =sales_data!H447 -> Аксессуары | ... Z72: =sales_data!O447 -> Отменён
L73: =sales_data!A463 -> 1044 | M73: =sales_data!B463 -> 45767 | N73: =sales_data!C463 -> 20 | O73: =sales_data!D463 -> Апрель | P73: =sales_data!E463 -> Павел | Q73: =sales_data!F463 -> Санкт-Петербург | R73: =sales_data!G463 -> Северо-Западный | S73: =sales_data!H463 -> Периферия | ... Z73: =sales_data!O463 -> В пути
L74: =sales_data!A474 -> 1778 | M74: =sales_data!B474 -> 45767 | N74: =sales_data!C474 -> 20 | O74: =sales_data!D474 -> Апрель | P74: =sales_data!E474 -> Павел | Q74: =sales_data!F474 -> Омск | R74: =sales_data!G474 -> Сибирский | S74: =sales_data!H474 -> Периферия | ... Z74: =sales_data!O474 -> Отменён
L75: =sales_data!A487 -> 2630 | M75: =sales_data!B487 -> 45834 | N75: =sales_data!C487 -> 26 | O75: =sales_data!D487 -> Июнь | P75: =sales_data!E487 -> Светлана | Q75: =sales_data!F487 -> Уфа | R75: =sales_data!G487 -> Приволжский | S75: =sales_data!H487 -> Периферия | ... Z75: =sales_data!O487 -> Доставлен
L76: =sales_data!A498 -> 3925 | M76: =sales_data!B498 -> 45717 | N76: =sales_data!C498 -> 1 | O76: =sales_data!D498 -> Март | P76: =sales_data!E498 -> Наталья | Q76: =sales_data!F498 -> Москва | R76: =sales_data!G498 -> Центральный | S76: =sales_data!H498 -> Периферия | ... Z76: =sales_data!O498 -> Отменён
L77: =sales_data!A500 -> 4201 | M77: =sales_data!B500 -> 45847 | N77: =sales_data!C500 -> 9 | O77: =sales_data!D500 -> Июль | P77: =sales_data!E500 -> Игорь | Q77: =sales_data!F500 -> Красноярск | R77: =sales_data!G500 -> Сибирский | S77: =sales_data!H500 -> Периферия | ... Z77: =sales_data!O500 -> В пути
L78: =sales_data!A503 -> 4266 | M78: =sales_data!B503 -> 45827 | N78: =sales_data!C503 -> 19 | O78: =sales_data!D503 -> Июнь | P78: =sales_data!E503 -> Елена | Q78: =sales_data!F503 -> Екатеринбург | R78: =sales_data!G503 -> Уральский | S78: =sales_data!H503 -> Периферия | ... Z78: =sales_data!O503 -> Доставлен
L79: =sales_data!A506 -> 4487 | M79: =sales_data!B506 -> 45688 | N79: =sales_data!C506 -> 31 | O79: =sales_data!D506 -> Январь | P79: =sales_data!E506 -> Светлана | Q79: =sales_data!F506 -> Краснодар | R79: =sales_data!G506 -> Южный | S79: =sales_data!H506 -> Периферия | ... Z79: =sales_data!O506 -> Доставлен
L80: =sales_data!A507 -> 4556 | M80: =sales_data!B507 -> 46010 | N80: =sales_data!C507 -> 19 | O80: =sales_data!D507 -> Декабрь | P80: =sales_data!E507 -> Ольга | Q80: =sales_data!F507 -> Уфа | R80: =sales_data!G507 -> Приволжский | S80: =sales_data!H507 -> Периферия | ... Z80: =sales_data!O507 -> Отменён
L81: =sales_data!A509 -> 4581 | M81: =sales_data!B509 -> 45875 | N81: =sales_data!C509 -> 6 | O81: =sales_data!D509 -> Август | P81: =sales_data!E509 -> Ксения | Q81: =sales_data!F509 -> Красноярск | R81: =sales_data!G509 -> Сибирский | S81: =sales_data!H509 -> Периферия | ... Z81: =sales_data!O509 -> Отменён
L82: =sales_data!A512 -> 4732 | M82: =sales_data!B512 -> 45744 | N82: =sales_data!C512 -> 28 | O82: =sales_data!D512 -> Март | P82: =sales_data!E512 -> Мария | Q82: =sales_data!F512 -> Москва | R82: =sales_data!G512 -> Центральный | S82: =sales_data!H512 -> Периферия | ... Z82: =sales_data!O512 -> В пути
L83: =sales_data!A515 -> 4916 | M83: =sales_data!B515 -> 45798 | N83: =sales_data!C515 -> 21 | O83: =sales_data!D515 -> Май | P83: =sales_data!E515 -> Борис | Q83: =sales_data!F515 -> Уфа | R83: =sales_data!G515 -> Приволжский | S83: =sales_data!H515 -> Периферия | ... Z83: =sales_data!O515 -> Отменён
L84: =sales_data!A521 -> 426 | M84: =sales_data!B521 -> 45936 | N84: =sales_data!C521 -> 6 | O84: =sales_data!D521 -> Октябрь | P84: =sales_data!E521 -> Наталья | Q84: =sales_data!F521 -> Челябинск | R84: =sales_data!G521 -> Уральский | S84: =sales_data!H521 -> Периферия | ... Z84: =sales_data!O521 -> Доставлен
L85: =sales_data!A535 -> 1229 | M85: =sales_data!B535 -> 45718 | N85: =sales_data!C535 -> 2 | O85: =sales_data!D535 -> Март | P85: =sales_data!E535 -> Мария | Q85: =sales_data!F535 -> Ростов-на-Дону | R85: =sales_data!G535 -> Южный | S85: =sales_data!H535 -> Периферия | ... Z85: =sales_data!O535 -> Доставлен
L86: =sales_data!A544 -> 1744 | M86: =sales_data!B544 -> 45916 | N86: =sales_data!C544 -> 16 | O86: =sales_data!D544 -> Сентябрь | P86: =sales_data!E544 -> Владимир | Q86: =sales_data!F544 -> Красноярск | R86: =sales_data!G544 -> Сибирский | S86: =sales_data!H544 -> Периферия | ... Z86: =sales_data!O544 -> Отменён
L87: =sales_data!A546 -> 1769 | M87: =sales_data!B546 -> 45870 | N87: =sales_data!C546 -> 1 | O87: =sales_data!D546 -> Август | P87: =sales_data!E546 -> Владимир | Q87: =sales_data!F546 -> Воронеж | R87: =sales_data!G546 -> Центральный | S87: =sales_data!H546 -> Аксессуары | ... Z87: =sales_data!O546 -> В пути
L88: =sales_data!A551 -> 2120 | M88: =sales_data!B551 -> 45914 | N88: =sales_data!C551 -> 14 | O88: =sales_data!D551 -> Сентябрь | P88: =sales_data!E551 -> Наталья | Q88: =sales_data!F551 -> Пермь | R88: =sales_data!G551 -> Приволжский | S88: =sales_data!H551 -> Аксессуары | ... Z88: =sales_data!O551 -> Доставлен
L89: =sales_data!A559 -> 2458 | M89: =sales_data!B559 -> 45786 | N89: =sales_data!C559 -> 9 | O89: =sales_data!D559 -> Май | P89: =sales_data!E559 -> Мария | Q89: =sales_data!F559 -> Красноярск | R89: =sales_data!G559 -> Сибирский | S89: =sales_data!H559 -> Аксессуары | ... Z89: =sales_data!O559 -> Доставлен
L90: =sales_data!A564 -> 2992 | M90: =sales_data!B564 -> 45872 | N90: =sales_data!C564 -> 3 | O90: =sales_data!D564 -> Август | P90: =sales_data!E564 -> Алексей | Q90: =sales_data!F564 -> Санкт-Петербург | R90: =sales_data!G564 -> Северо-Западный | S90: =sales_data!H564 -> Периферия | ... Z90: =sales_data!O564 -> Доставлен
L91: =sales_data!A571 -> 3458 | M91: =sales_data!B571 -> 45974 | N91: =sales_data!C571 -> 13 | O91: =sales_data!D571 -> Ноябрь | P91: =sales_data!E571 -> Дмитрий | Q91: =sales_data!F571 -> Челябинск | R91: =sales_data!G571 -> Уральский | S91: =sales_data!H571 -> Аксессуары | ... Z91: =sales_data!O571 -> Доставлен
L92: =sales_data!A579 -> 3853 | M92: =sales_data!B579 -> 45667 | N92: =sales_data!C579 -> 10 | O92: =sales_data!D579 -> Январь | P92: =sales_data!E579 -> Игорь | Q92: =sales_data!F579 -> Краснодар | R92: =sales_data!G579 -> Южный | S92: =sales_data!H579 -> Периферия | ... Z92: =sales_data!O579 -> Отменён
L93: =sales_data!A584 -> 4081 | M93: =sales_data!B584 -> 45771 | N93: =sales_data!C584 -> 24 | O93: =sales_data!D584 -> Апрель | P93: =sales_data!E584 -> Татьяна | Q93: =sales_data!F584 -> Челябинск | R93: =sales_data!G584 -> Уральский | S93: =sales_data!H584 -> Периферия | ... Z93: =sales_data!O584 -> Доставлен
L94: =sales_data!A586 -> 4239 | M94: =sales_data!B586 -> 45734 | N94: =sales_data!C586 -> 18 | O94: =sales_data!D586 -> Март | P94: =sales_data!E586 -> Игорь | Q94: =sales_data!F586 -> Ростов-на-Дону | R94: =sales_data!G586 -> Южный | S94: =sales_data!H586 -> Периферия | ... Z94: =sales_data!O586 -> Отменён
L95: =sales_data!A595 -> 4899 | M95: =sales_data!B595 -> 45967 | N95: =sales_data!C595 -> 6 | O95: =sales_data!D595 -> Ноябрь | P95: =sales_data!E595 -> Алексей | Q95: =sales_data!F595 -> Уфа | R95: =sales_data!G595 -> Приволжский | S95: =sales_data!H595 -> Периферия | ... Z95: =sales_data!O595 -> Доставлен
L96: =sales_data!A596 -> 4972 | M96: =sales_data!B596 -> 45968 | N96: =sales_data!C596 -> 7 | O96: =sales_data!D596 -> Ноябрь | P96: =sales_data!E596 -> Светлана | Q96: =sales_data!F596 -> Омск | R96: =sales_data!G596 -> Сибирский | S96: =sales_data!H596 -> Аксессуары | ... Z96: =sales_data!O596 -> Отменён
L97: =sales_data!A601 -> 189 | M97: =sales_data!B601 -> 45856 | N97: =sales_data!C601 -> 18 | O97: =sales_data!D601 -> Июль | P97: =sales_data!E601 -> Ольга | Q97: =sales_data!F601 -> Красноярск | R97: =sales_data!G601 -> Сибирский | S97: =sales_data!H601 -> Периферия | ... Z97: =sales_data!O601 -> В пути
L98: =sales_data!A606 -> 775 | M98: =sales_data!B606 -> 45807 | N98: =sales_data!C606 -> 30 | O98: =sales_data!D606 -> Май | P98: =sales_data!E606 -> Ольга | Q98: =sales_data!F606 -> Омск | R98: =sales_data!G606 -> Сибирский | S98: =sales_data!H606 -> Аксессуары | ... Z98: =sales_data!O606 -> В пути
L99: =sales_data!A607 -> 942 | M99: =sales_data!B607 -> 45984 | N99: =sales_data!C607 -> 23 | O99: =sales_data!D607 -> Ноябрь | P99: =sales_data!E607 -> Мария | Q99: =sales_data!F607 -> Красноярск | R99: =sales_data!G607 -> Сибирский | S99: =sales_data!H607 -> Аксессуары | ... Z99: =sales_data!O607 -> В пути
L100: =sales_data!A614 -> 1460 | M100: =sales_data!B614 -> 45814 | N100: =sales_data!C614 -> 6 | O100: =sales_data!D614 -> Июнь | P100: =sales_data!E614 -> Борис | Q100: =sales_data!F614 -> Екатеринбург | R100: =sales_data!G614 -> Уральский | S100: =sales_data!H614 -> Аксессуары | ... Z100: =sales_data!O614 -> Доставлен
L101: =sales_data!A617 -> 1698 | M101: =sales_data!B617 -> 45721 | N101: =sales_data!C617 -> 5 | O101: =sales_data!D617 -> Март | P101: =sales_data!E617 -> Борис | Q101: =sales_data!F617 -> Казань | R101: =sales_data!G617 -> Приволжский | S101: =sales_data!H617 -> Периферия | ... Z101: =sales_data!O617 -> В пути
...

Sheet 3_Фильтр_2
A1: Шаг 3. Фильтрация по двум условиям: city == "Москва" и channel == "Онлайн"
A3: order_id | B3: client | C3: city | D3: category | E3: product | F3: quantity | G3: price | H3: manager | I3: channel | J3: flag_москва_онлайн | L3: order_id | M3: date | N3: day | O3: month | P3: manager | Q3: city | R3: region | S3: category | T3: product | U3: client_type | V3: quantity | W3: price_per_unit | X3: revenue | Y3: channel | Z3: status
A4: 201 | B4: ООО Альфа | C4: Москва | D4: Ноутбуки | E4: Notebook Air | F4: 2 | G4: 55000 | H4: Анна | I4: Онлайн | J4: =IF(AND(C4="Москва",I4="Онлайн"),"Да","Нет") -> Да | L4: =sales_data!A3 -> 85 | M4: =sales_data!B3 -> 45881 | N4: =sales_data!C3 -> 12 | O4: =sales_data!D3 -> Август | P4: =sales_data!E3 -> Владимир | Q4: =sales_data!F3 -> Уфа | R4: =sales_data!G3 -> Приволжский | S4: =sales_data!H3 -> Аксессуары | ... Z4: =sales_data!O3 -> В пути
A5: 202 | B5: ООО Бета | C5: Санкт-Петербург | D5: Мониторы | E5: Monitor 27 | F5: 1 | G5: 23000 | H5: Борис | I5: Офлайн | J5: =IF(AND(C5="Москва",I5="Онлайн"),"Да","Нет") -> Нет | L5: =sales_data!A73 -> 2784 | M5: =sales_data!B73 -> 45961 | N5: =sales_data!C73 -> 31 | O5: =sales_data!D73 -> Октябрь | P5: =sales_data!E73 -> Ксения | Q5: =sales_data!F73 -> Пермь | R5: =sales_data!G73 -> Приволжский | S5: =sales_data!H73 -> Аксессуары | ... Z5: =sales_data!O73 -> В пути
A6: 203 | B6: ИП Гамма | C6: Москва | D6: Ноутбуки | E6: Notebook Pro | F6: 3 | G6: 72000 | H6: Анна | I6: Онлайн | J6: =IF(AND(C6="Москва",I6="Онлайн"),"Да","Нет") -> Да | L6: =sales_data!A79 -> 3175 | M6: =sales_data!B79 -> 45829 | N6: =sales_data!C79 -> 21 | O6: =sales_data!D79 -> Июнь | P6: =sales_data!E79 -> Мария | Q6: =sales_data!F79 -> Екатеринбург | R6: =sales_data!G79 -> Уральский | S6: =sales_data!H79 -> Аксессуары | ... Z6: =sales_data!O79 -> В пути
A7: 204 | B7: ООО Дельта | C7: Казань | D7: Периферия | E7: Mouse Pro | F7: 5 | G7: 2500 | H7: Виктор | I7: Маркетплейс | J7: =IF(AND(C7="Москва",I7="Онлайн"),"Да","Нет") -> Нет | L7: =sales_data!A103 -> 59 | M7: =sales_data!B103 -> 45804 | N7: =sales_data!C103 -> 27 | O7: =sales_data!D103 -> Май | P7: =sales_data!E103 -> Дмитрий | Q7: =sales_data!F103 -> Нижний Новгород | R7: =sales_data!G103 -> Приволжский | S7: =sales_data!H103 -> Аксессуары | ... Z7: =sales_data!O103 -> В пути
A8: 205 | B8: ООО Эпсилон | C8: Москва | D8: Мониторы | E8: Monitor 24 | F8: 2 | G8: 18000 | H8: Анна | I8: Онлайн | J8: =IF(AND(C8="Москва",I8="Онлайн"),"Да","Нет") -> Да | L8: =sales_data!A110 -> 248 | M8: =sales_data!B110 -> 45892 | N8: =sales_data!C110 -> 23 | O8: =sales_data!D110 -> Август | P8: =sales_data!E110 -> Дмитрий | Q8: =sales_data!F110 -> Новосибирск | R8: =sales_data!G110 -> Сибирский | S8: =sales_data!H110 -> Аксессуары | ... Z8: =sales_data!O110 -> В пути
A9: 206 | B9: ИП Жасмин | C9: Екатеринбург | D9: Ноутбуки | E9: Notebook Lite | F9: 1 | G9: 49000 | H9: Борис | I9: Офлайн | J9: =IF(AND(C9="Москва",I9="Онлайн"),"Да","Нет") -> Нет | L9: =sales_data!A146 -> 2192 | M9: =sales_data!B146 -> 45708 | N9: =sales_data!C146 -> 20 | O9: =sales_data!D146 -> Февраль | P9: =sales_data!E146 -> Павел | Q9: =sales_data!F146 -> Красноярск | R9: =sales_data!G146 -> Сибирский | S9: =sales_data!H146 -> Аксессуары | ... Z9: =sales_data!O146 -> Отменён
A10: 207 | B10: ООО Зета | C10: Москва | D10: Периферия | E10: Keyboard X | F10: 4 | G10: 4000 | H10: Виктор | I10: Онлайн | J10: =IF(AND(C10="Москва",I10="Онлайн"),"Да","Нет") -> Да | L10: =sales_data!A157 -> 2757 | M10: =sales_data!B157 -> 45711 | N10: =sales_data!C157 -> 23 | O10: =sales_data!D157 -> Февраль | P10: =sales_data!E157 -> Дмитрий | Q10: =sales_data!F157 -> Нижний Новгород | R10: =sales_data!G157 -> Приволжский | S10: =sales_data!H157 -> Аксессуары | ... Z10: =sales_data!O157 -> Доставлен
A11: 208 | B11: ООО Ита | C11: Новосибирск | D11: Ноутбуки | E11: Notebook Air | F11: 2 | G11: 55000 | H11: Анна | I11: Маркетплейс | J11: =IF(AND(C11="Москва",I11="Онлайн"),"Да","Нет") -> Нет | L11: =sales_data!A209 -> 419 | M11: =sales_data!B209 -> 45980 | N11: =sales_data!C209 -> 19 | O11: =sales_data!D209 -> Ноябрь | P11: =sales_data!E209 -> Татьяна | Q11: =sales_data!F209 -> Санкт-Петербург | R11: =sales_data!G209 -> Северо-Западный | S11: =sales_data!H209 -> Аксессуары | ... Z11: =sales_data!O209 -> Доставлен
A12: 209 | B12: ООО Каппа | C12: Москва | D12: Ноутбуки | E12: Notebook Start | F12: 1 | G12: 43000 | H12: Борис | I12: Офлайн | J12: =IF(AND(C12="Москва",I12="Онлайн"),"Да","Нет") -> Нет | L12: =sales_data!A260 -> 423 | M12: =sales_data!B260 -> 45734 | N12: =sales_data!C260 -> 18 | O12: =sales_data!D260 -> Март | P12: =sales_data!E260 -> Анна | Q12: =sales_data!F260 -> Омск | R12: =sales_data!G260 -> Сибирский | S12: =sales_data!H260 -> Аксессуары | ... Z12: =sales_data!O260 -> В пути
L13: =sales_data!A332 -> 3847 | M13: =sales_data!B332 -> 45860 | N13: =sales_data!C332 -> 22 | O13: =sales_data!D332 -> Июль | P13: =sales_data!E332 -> Анна | Q13: =sales_data!F332 -> Челябинск | R13: =sales_data!G332 -> Уральский | S13: =sales_data!H332 -> Аксессуары | ... Z13: =sales_data!O332 -> Доставлен
L14: =sales_data!A347 -> 3212 | M14: =sales_data!B347 -> 46007 | N14: =sales_data!C347 -> 16 | O14: =sales_data!D347 -> Декабрь | P14: =sales_data!E347 -> Светлана | Q14: =sales_data!F347 -> Новосибирск | R14: =sales_data!G347 -> Сибирский | S14: =sales_data!H347 -> Аксессуары | ... Z14: =sales_data!O347 -> Доставлен
L15: =sales_data!A369 -> 1716 | M15: =sales_data!B369 -> 45782 | N15: =sales_data!C369 -> 5 | O15: =sales_data!D369 -> Май | P15: =sales_data!E369 -> Сергей | Q15: =sales_data!F369 -> Красноярск | R15: =sales_data!G369 -> Сибирский | S15: =sales_data!H369 -> Аксессуары | ... Z15: =sales_data!O369 -> В пути
L16: =sales_data!A417 -> 2806 | M16: =sales_data!B417 -> 45955 | N16: =sales_data!C417 -> 25 | O16: =sales_data!D417 -> Октябрь | P16: =sales_data!E417 -> Елена | Q16: =sales_data!F417 -> Уфа | R16: =sales_data!G417 -> Приволжский | S16: =sales_data!H417 -> Аксессуары | ... Z16: =sales_data!O417 -> Отменён
L17: =sales_data!A418 -> 2892 | M17: =sales_data!B418 -> 45877 | N17: =sales_data!C418 -> 8 | O17: =sales_data!D418 -> Август | P17: =sales_data!E418 -> Наталья | Q17: =sales_data!F418 -> Воронеж | R17: =sales_data!G418 -> Центральный | S17: =sales_data!H418 -> Аксессуары | ... Z17: =sales_data!O418 -> В пути
L18: =sales_data!A440 -> 4941 | M18: =sales_data!B440 -> 45834 | N18: =sales_data!C440 -> 26 | O18: =sales_data!D440 -> Июнь | P18: =sales_data!E440 -> Борис | Q18: =sales_data!F440 -> Красноярск | R18: =sales_data!G440 -> Сибирский | S18: =sales_data!H440 -> Аксессуары | ... Z18: =sales_data!O440 -> В пути
L19: =sales_data!A471 -> 1545 | M19: =sales_data!B471 -> 45719 | N19: =sales_data!C471 -> 3 | O19: =sales_data!D471 -> Март | P19: =sales_data!E471 -> Ольга | Q19: =sales_data!F471 -> Екатеринбург | R19: =sales_data!G471 -> Уральский | S19: =sales_data!H471 -> Аксессуары | ... Z19: =sales_data!O471 -> В пути
L20: =sales_data!A483 -> 2282 | M20: =sales_data!B483 -> 45672 | N20: =sales_data!C483 -> 15 | O20: =sales_data!D483 -> Январь | P20: =sales_data!E483 -> Игорь | Q20: =sales_data!F483 -> Новосибирск | R20: =sales_data!G483 -> Сибирский | S20: =sales_data!H483 -> Аксессуары | ... Z20: =sales_data!O483 -> В пути
L21: =sales_data!A499 -> 4017 | M21: =sales_data!B499 -> 45806 | N21: =sales_data!C499 -> 29 | O21: =sales_data!D499 -> Май | P21: =sales_data!E499 -> Светлана | Q21: =sales_data!F499 -> Москва | R21: =sales_data!G499 -> Центральный | S21: =sales_data!H499 -> Периферия | ... Z21: =sales_data!O499 -> Отменён
L22: =sales_data!A521 -> 426 | M22: =sales_data!B521 -> 45936 | N22: =sales_data!C521 -> 6 | O22: =sales_data!D521 -> Октябрь | P22: =sales_data!E521 -> Наталья | Q22: =sales_data!F521 -> Челябинск | R22: =sales_data!G521 -> Уральский | S22: =sales_data!H521 -> Периферия | ... Z22: =sales_data!O521 -> Доставлен
L23: =sales_data!A554 -> 2293 | M23: =sales_data!B554 -> 45889 | N23: =sales_data!C554 -> 20 | O23: =sales_data!D554 -> Август | P23: =sales_data!E554 -> Татьяна | Q23: =sales_data!F554 -> Самара | R23: =sales_data!G554 -> Приволжский | S23: =sales_data!H554 -> Аксессуары | ... Z23: =sales_data!O554 -> В пути
L24: =sales_data!A572 -> 3461 | M24: =sales_data!B572 -> 45921 | N24: =sales_data!C572 -> 21 | O24: =sales_data!D572 -> Сентябрь | P24: =sales_data!E572 -> Алексей | Q24: =sales_data!F572 -> Краснодар | R24: =sales_data!G572 -> Южный | S24: =sales_data!H572 -> Периферия | ... Z24: =sales_data!O572 -> Отменён
L25: =sales_data!A574 -> 3484 | M25: =sales_data!B574 -> 45883 | N25: =sales_data!C574 -> 14 | O25: =sales_data!D574 -> Август | P25: =sales_data!E574 -> Мария | Q25: =sales_data!F574 -> Екатеринбург | R25: =sales_data!G574 -> Уральский | S25: =sales_data!H574 -> Аксессуары | ... Z25: =sales_data!O574 -> Отменён
L26: =sales_data!A609 -> 1064 | M26: =sales_data!B609 -> 45780 | N26: =sales_data!C609 -> 3 | O26: =sales_data!D609 -> Май | P26: =sales_data!E609 -> Наталья | Q26: =sales_data!F609 -> Омск | R26: =sales_data!G609 -> Сибирский | S26: =sales_data!H609 -> Аксессуары | ... Z26: =sales_data!O609 -> Доставлен
L27: =sales_data!A651 -> 4800 | M27: =sales_data!B651 -> 46002 | N27: =sales_data!C651 -> 11 | O27: =sales_data!D651 -> Декабрь | P27: =sales_data!E651 -> Владимир | Q27: =sales_data!F651 -> Красноярск | R27: =sales_data!G651 -> Сибирский | S27: =sales_data!H651 -> Аксессуары | ... Z27: =sales_data!O651 -> Доставлен
L28: =sales_data!A660 -> 687 | M28: =sales_data!B660 -> 45981 | N28: =sales_data!C660 -> 20 | O28: =sales_data!D660 -> Ноябрь | P28: =sales_data!E660 -> Ольга | Q28: =sales_data!F660 -> Москва | R28: =sales_data!G660 -> Центральный | S28: =sales_data!H660 -> Периферия | ... Z28: =sales_data!O660 -> В пути
L29: =sales_data!A668 -> 1054 | M29: =sales_data!B668 -> 45777 | N29: =sales_data!C668 -> 30 | O29: =sales_data!D668 -> Апрель | P29: =sales_data!E668 -> Ксения | Q29: =sales_data!F668 -> Нижний Новгород | R29: =sales_data!G668 -> Приволжский | S29: =sales_data!H668 -> Периферия | ... Z29: =sales_data!O668 -> Отменён
L30: =sales_data!A675 -> 1607 | M30: =sales_data!B675 -> 45768 | N30: =sales_data!C675 -> 21 | O30: =sales_data!D675 -> Апрель | P30: =sales_data!E675 -> Елена | Q30: =sales_data!F675 -> Казань | R30: =sales_data!G675 -> Приволжский | S30: =sales_data!H675 -> Периферия | ... Z30: =sales_data!O675 -> В пути
L31: =sales_data!A682 -> 2198 | M31: =sales_data!B682 -> 45843 | N31: =sales_data!C682 -> 5 | O31: =sales_data!D682 -> Июль | P31: =sales_data!E682 -> Алексей | Q31: =sales_data!F682 -> Самара | R31: =sales_data!G682 -> Приволжский | S31: =sales_data!H682 -> Периферия | ... Z31: =sales_data!O682 -> Отменён
L32: =sales_data!A687 -> 2759 | M32: =sales_data!B687 -> 46002 | N32: =sales_data!C687 -> 11 | O32: =sales_data!D687 -> Декабрь | P32: =sales_data!E687 -> Мария | Q32: =sales_data!F687 -> Пермь | R32: =sales_data!G687 -> Приволжский | S32: =sales_data!H687 -> Аксессуары | ... Z32: =sales_data!O687 -> Отменён
L33: =sales_data!A689 -> 2785 | M33: =sales_data!B689 -> 45807 | N33: =sales_data!C689 -> 30 | O33: =sales_data!D689 -> Май | P33: =sales_data!E689 -> Борис | Q33: =sales_data!F689 -> Самара | R33: =sales_data!G689 -> Приволжский | S33: =sales_data!H689 -> Периферия | ... Z33: =sales_data!O689 -> В пути
L34: =sales_data!A729 -> 1153 | M34: =sales_data!B729 -> 45894 | N34: =sales_data!C729 -> 25 | O34: =sales_data!D729 -> Август | P34: =sales_data!E729 -> Борис | Q34: =sales_data!F729 -> Санкт-Петербург | R34: =sales_data!G729 -> Северо-Западный | S34: =sales_data!H729 -> Аксессуары | ... Z34: =sales_data!O729 -> В пути
L35: =sales_data!A793 -> 573 | M35: =sales_data!B793 -> 45739 | N35: =sales_data!C793 -> 23 | O35: =sales_data!D793 -> Март | P35: =sales_data!E793 -> Светлана | Q35: =sales_data!F793 -> Омск | R35: =sales_data!G793 -> Сибирский | S35: =sales_data!H793 -> Аксессуары | ... Z35: =sales_data!O793 -> Доставлен
L36: =sales_data!A824 -> 2706 | M36: =sales_data!B824 -> 45996 | N36: =sales_data!C824 -> 5 | O36: =sales_data!D824 -> Декабрь | P36: =sales_data!E824 -> Наталья | Q36: =sales_data!F824 -> Казань | R36: =sales_data!G824 -> Приволжский | S36: =sales_data!H824 -> Периферия | ... Z36: =sales_data!O824 -> Отменён
L37: =sales_data!A836 -> 3688 | M37: =sales_data!B836 -> 45797 | N37: =sales_data!C836 -> 20 | O37: =sales_data!D836 -> Май | P37: =sales_data!E836 -> Борис | Q37: =sales_data!F836 -> Пермь | R37: =sales_data!G836 -> Приволжский | S37: =sales_data!H836 -> Аксессуары | ... Z37: =sales_data!O836 -> Отменён
L38: =sales_data!A858 -> 1084 | M38: =sales_data!B858 -> 45691 | N38: =sales_data!C858 -> 3 | O38: =sales_data!D858 -> Февраль | P38: =sales_data!E858 -> Светлана | Q38: =sales_data!F858 -> Екатеринбург | R38: =sales_data!G858 -> Уральский | S38: =sales_data!H858 -> Аксессуары | ... Z38: =sales_data!O858 -> Отменён
L39: =sales_data!A879 -> 3749 | M39: =sales_data!B879 -> 45858 | N39: =sales_data!C879 -> 20 | O39: =sales_data!D879 -> Июль | P39: =sales_data!E879 -> Павел | Q39: =sales_data!F879 -> Самара | R39: =sales_data!G879 -> Приволжский | S39: =sales_data!H879 -> Периферия | ... Z39: =sales_data!O879 -> В пути
L40: =sales_data!A895 -> 1234 | M40: =sales_data!B895 -> 46013 | N40: =sales_data!C895 -> 22 | O40: =sales_data!D895 -> Декабрь | P40: =sales_data!E895 -> Алексей | Q40: =sales_data!F895 -> Санкт-Петербург | R40: =sales_data!G895 -> Северо-Западный | S40: =sales_data!H895 -> Аксессуары | ... Z40: =sales_data!O895 -> В пути
L41: =sales_data!A910 -> 2398 | M41: =sales_data!B910 -> 45897 | N41: =sales_data!C910 -> 28 | O41: =sales_data!D910 -> Август | P41: =sales_data!E910 -> Борис | Q41: =sales_data!F910 -> Воронеж | R41: =sales_data!G910 -> Центральный | S41: =sales_data!H910 -> Периферия | ... Z41: =sales_data!O910 -> Отменён
L42: =sales_data!A949 -> 42 | M42: =sales_data!B949 -> 45711 | N42: =sales_data!C949 -> 23 | O42: =sales_data!D949 -> Февраль | P42: =sales_data!E949 -> Ксения | Q42: =sales_data!F949 -> Казань | R42: =sales_data!G949 -> Приволжский | S42: =sales_data!H949 -> Периферия | ... Z42: =sales_data!O949 -> В пути
L43: =sales_data!A1088 -> 4390 | M43: =sales_data!B1088 -> 45700 | N43: =sales_data!C1088 -> 12 | O43: =sales_data!D1088 -> Февраль | P43: =sales_data!E1088 -> Игорь | Q43: =sales_data!F1088 -> Самара | R43: =sales_data!G1088 -> Приволжский | S43: =sales_data!H1088 -> Аксессуары | ... Z43: =sales_data!O1088 -> Доставлен
L44: =sales_data!A1091 -> 4608 | M44: =sales_data!B1091 -> 45829 | N44: =sales_data!C1091 -> 21 | O44: =sales_data!D1091 -> Июнь | P44: =sales_data!E1091 -> Ксения | Q44: =sales_data!F1091 -> Уфа | R44: =sales_data!G1091 -> Приволжский | S44: =sales_data!H1091 -> Аксессуары | ... Z44: =sales_data!O1091 -> Доставлен
L45: =sales_data!A1161 -> 1745 | M45: =sales_data!B1161 -> 45692 | N45: =sales_data!C1161 -> 4 | O45: =sales_data!D1161 -> Февраль | P45: =sales_data!E1161 -> Алексей | Q45: =sales_data!F1161 -> Санкт-Петербург | R45: =sales_data!G1161 -> Северо-Западный | S45: =sales_data!H1161 -> Аксессуары | ... Z45: =sales_data!O1161 -> Отменён
L46: =sales_data!A1177 -> 2902 | M46: =sales_data!B1177 -> 45864 | N46: =sales_data!C1177 -> 26 | O46: =sales_data!D1177 -> Июль | P46: =sales_data!E1177 -> Павел | Q46: =sales_data!F1177 -> Новосибирск | R46: =sales_data!G1177 -> Сибирский | S46: =sales_data!H1177 -> Аксессуары | ... Z46: =sales_data!O1177 -> Доставлен
L47: =sales_data!A1249 -> 3237 | M47: =sales_data!B1249 -> 45805 | N47: =sales_data!C1249 -> 28 | O47: =sales_data!D1249 -> Май | P47: =sales_data!E1249 -> Мария | Q47: =sales_data!F1249 -> Воронеж | R47: =sales_data!G1249 -> Центральный | S47: =sales_data!H1249 -> Периферия | ... Z47: =sales_data!O1249 -> Отменён
L48: =sales_data!A1275 -> 3276 | M48: =sales_data!B1275 -> 45934 | N48: =sales_data!C1275 -> 4 | O48: =sales_data!D1275 -> Октябрь | P48: =sales_data!E1275 -> Мария | Q48: =sales_data!F1275 -> Казань | R48: =sales_data!G1275 -> Приволжский | S48: =sales_data!H1275 -> Периферия | ... Z48: =sales_data!O1275 -> Отменён
L49: =sales_data!A1296 -> 1787 | M49: =sales_data!B1296 -> 45800 | N49: =sales_data!C1296 -> 23 | O49: =sales_data!D1296 -> Май | P49: =sales_data!E1296 -> Анна | Q49: =sales_data!F1296 -> Нижний Новгород | R49: =sales_data!G1296 -> Приволжский | S49: =sales_data!H1296 -> Периферия | ... Z49: =sales_data!O1296 -> В пути
L50: =sales_data!A1329 -> 234 | M50: =sales_data!B1329 -> 45896 | N50: =sales_data!C1329 -> 27 | O50: =sales_data!D1329 -> Август | P50: =sales_data!E1329 -> Татьяна | Q50: =sales_data!F1329 -> Самара | R50: =sales_data!G1329 -> Приволжский | S50: =sales_data!H1329 -> Периферия | ... Z50: =sales_data!O1329 -> Отменён
L51: =sales_data!A1336 -> 1366 | M51: =sales_data!B1336 -> 45810 | N51: =sales_data!C1336 -> 2 | O51: =sales_data!D1336 -> Июнь | P51: =sales_data!E1336 -> Светлана | Q51: =sales_data!F1336 -> Новосибирск | R51: =sales_data!G1336 -> Сибирский | S51: =sales_data!H1336 -> Периферия | ... Z51: =sales_data!O1336 -> Отменён
L52: =sales_data!A1345 -> 2454 | M52: =sales_data!B1345 -> 45829 | N52: =sales_data!C1345 -> 21 | O52: =sales_data!D1345 -> Июнь | P52: =sales_data!E1345 -> Сергей | Q52: =sales_data!F1345 -> Омск | R52: =sales_data!G1345 -> Сибирский | S52: =sales_data!H1345 -> Периферия | ... Z52: =sales_data!O1345 -> Доставлен
L53: =sales_data!A1504 -> 3244 | M53: =sales_data!B1504 -> 45952 | N53: =sales_data!C1504 -> 22 | O53: =sales_data!D1504 -> Октябрь | P53: =sales_data!E1504 -> Сергей | Q53: =sales_data!F1504 -> Самара | R53: =sales_data!G1504 -> Приволжский | S53: =sales_data!H1504 -> Периферия | ... Z53: =sales_data!O1504 -> Отменён
L54: =sales_data!A1507 -> 4424 | M54: =sales_data!B1507 -> 45978 | N54: =sales_data!C1507 -> 17 | O54: =sales_data!D1507 -> Ноябрь | P54: =sales_data!E1507 -> Ксения | Q54: =sales_data!F1507 -> Москва | R54: =sales_data!G1507 -> Центральный | S54: =sales_data!H1507 -> Периферия | ... Z54: =sales_data!O1507 -> Отменён
L55: =sales_data!A1520 -> 1879 | M55: =sales_data!B1520 -> 45987 | N55: =sales_data!C1520 -> 26 | O55: =sales_data!D1520 -> Ноябрь | P55: =sales_data!E1520 -> Елена | Q55: =sales_data!F1520 -> Новосибирск | R55: =sales_data!G1520 -> Сибирский | S55: =sales_data!H1520 -> Принтеры | ... Z55: =sales_data!O1520 -> В пути
L56: =sales_data!A1527 -> 3006 | M56: =sales_data!B1527 -> 45752 | N56: =sales_data!C1527 -> 5 | O56: =sales_data!D1527 -> Апрель | P56: =sales_data!E1527 -> Ольга | Q56: =sales_data!F1527 -> Пермь | R56: =sales_data!G1527 -> Приволжский | S56: =sales_data!H1527 -> Принтеры | ... Z56: =sales_data!O1527 -> Отменён
L57: =sales_data!A1532 -> 3411 | M57: =sales_data!B1532 -> 45889 | N57: =sales_data!C1532 -> 20 | O57: =sales_data!D1532 -> Август | P57: =sales_data!E1532 -> Игорь | Q57: =sales_data!F1532 -> Ростов-на-Дону | R57: =sales_data!G1532 -> Южный | S57: =sales_data!H1532 -> Принтеры | ... Z57: =sales_data!O1532 -> Доставлен
L58: =sales_data!A1536 -> 4516 | M58: =sales_data!B1536 -> 45983 | N58: =sales_data!C1536 -> 22 | O58: =sales_data!D1536 -> Ноябрь | P58: =sales_data!E1536 -> Павел | Q58: =sales_data!F1536 -> Воронеж | R58: =sales_data!G1536 -> Центральный | S58: =sales_data!H1536 -> Принтеры | ... Z58: =sales_data!O1536 -> Доставлен
L59: =sales_data!A1617 -> 2843 | M59: =sales_data!B1617 -> 45850 | N59: =sales_data!C1617 -> 12 | O59: =sales_data!D1617 -> Июль | P59: =sales_data!E1617 -> Дмитрий | Q59: =sales_data!F1617 -> Омск | R59: =sales_data!G1617 -> Сибирский | S59: =sales_data!H1617 -> Принтеры | ... Z59: =sales_data!O1617 -> Доставлен
L60: =sales_data!A1621 -> 4164 | M60: =sales_data!B1621 -> 46006 | N60: =sales_data!C1621 -> 15 | O60: =sales_data!D1621 -> Декабрь | P60: =sales_data!E1621 -> Дмитрий | Q60: =sales_data!F1621 -> Красноярск | R60: =sales_data!G1621 -> Сибирский | S60: =sales_data!H1621 -> Принтеры | ... Z60: =sales_data!O1621 -> В пути
L61: =sales_data!A1625 -> 3072 | M61: =sales_data!B1625 -> 45847 | N61: =sales_data!C1625 -> 9 | O61: =sales_data!D1625 -> Июль | P61: =sales_data!E1625 -> Алексей | Q61: =sales_data!F1625 -> Новосибирск | R61: =sales_data!G1625 -> Сибирский | S61: =sales_data!H1625 -> Принтеры | ... Z61: =sales_data!O1625 -> В пути
L62: =sales_data!A1633 -> 2668 | M62: =sales_data!B1633 -> 45819 | N62: =sales_data!C1633 -> 11 | O62: =sales_data!D1633 -> Июнь | P62: =sales_data!E1633 -> Алексей | Q62: =sales_data!F1633 -> Новосибирск | R62: =sales_data!G1633 -> Сибирский | S62: =sales_data!H1633 -> Принтеры | ... Z62: =sales_data!O1633 -> В пути
L63: =sales_data!A1768 -> 105 | M63: =sales_data!B1768 -> 45949 | N63: =sales_data!C1768 -> 19 | O63: =sales_data!D1768 -> Октябрь | P63: =sales_data!E1768 -> Ксения | Q63: =sales_data!F1768 -> Екатеринбург | R63: =sales_data!G1768 -> Уральский | S63: =sales_data!H1768 -> Принтеры | ... Z63: =sales_data!O1768 -> Отменён
L64: =sales_data!A1808 -> 2879 | M64: =sales_data!B1808 -> 45762 | N64: =sales_data!C1808 -> 15 | O64: =sales_data!D1808 -> Апрель | P64: =sales_data!E1808 -> Мария | Q64: =sales_data!F1808 -> Пермь | R64: =sales_data!G1808 -> Приволжский | S64: =sales_data!H1808 -> Принтеры | ... Z64: =sales_data!O1808 -> В пути
L65: =sales_data!A1863 -> 4639 | M65: =sales_data!B1863 -> 45886 | N65: =sales_data!C1863 -> 17 | O65: =sales_data!D1863 -> Август | P65: =sales_data!E1863 -> Наталья | Q65: =sales_data!F1863 -> Пермь | R65: =sales_data!G1863 -> Приволжский | S65: =sales_data!H1863 -> Принтеры | ... Z65: =sales_data!O1863 -> Отменён
L66: =sales_data!A1882 -> 2396 | M66: =sales_data!B1882 -> 45674 | N66: =sales_data!C1882 -> 17 | O66: =sales_data!D1882 -> Январь | P66: =sales_data!E1882 -> Анна | Q66: =sales_data!F1882 -> Екатеринбург | R66: =sales_data!G1882 -> Уральский | S66: =sales_data!H1882 -> Принтеры | ... Z66: =sales_data!O1882 -> В пути
L67: =sales_data!A1911 -> 2570 | M67: =sales_data!B1911 -> 45963 | N67: =sales_data!C1911 -> 2 | O67: =sales_data!D1911 -> Ноябрь | P67: =sales_data!E1911 -> Светлана | Q67: =sales_data!F1911 -> Москва | R67: =sales_data!G1911 -> Центральный | S67: =sales_data!H1911 -> Принтеры | ... Z67: =sales_data!O1911 -> Доставлен
L68: =sales_data!A1936 -> 1531 | M68: =sales_data!B1936 -> 45713 | N68: =sales_data!C1936 -> 25 | O68: =sales_data!D1936 -> Февраль | P68: =sales_data!E1936 -> Борис | Q68: =sales_data!F1936 -> Самара | R68: =sales_data!G1936 -> Приволжский | S68: =sales_data!H1936 -> Принтеры | ... Z68: =sales_data!O1936 -> В пути
L69: =sales_data!A1965 -> 3623 | M69: =sales_data!B1965 -> 45788 | N69: =sales_data!C1965 -> 11 | O69: =sales_data!D1965 -> Май | P69: =sales_data!E1965 -> Светлана | Q69: =sales_data!F1965 -> Челябинск | R69: =sales_data!G1965 -> Уральский | S69: =sales_data!H1965 -> Периферия | ... Z69: =sales_data!O1965 -> Доставлен
L70: =sales_data!A1967 -> 4404 | M70: =sales_data!B1967 -> 45773 | N70: =sales_data!C1967 -> 26 | O70: =sales_data!D1967 -> Апрель | P70: =sales_data!E1967 -> Светлана | Q70: =sales_data!F1967 -> Москва | R70: =sales_data!G1967 -> Центральный | S70: =sales_data!H1967 -> Принтеры | ... Z70: =sales_data!O1967 -> Отменён
L71: =sales_data!A1971 -> 242 | M71: =sales_data!B1971 -> 45688 | N71: =sales_data!C1971 -> 31 | O71: =sales_data!D1971 -> Январь | P71: =sales_data!E1971 -> Светлана | Q71: =sales_data!F1971 -> Челябинск | R71: =sales_data!G1971 -> Уральский | S71: =sales_data!H1971 -> Принтеры | ... Z71: =sales_data!O1971 -> Отменён
L72: =sales_data!A2003 -> 868 | M72: =sales_data!B2003 -> 45988 | N72: =sales_data!C2003 -> 27 | O72: =sales_data!D2003 -> Ноябрь | P72: =sales_data!E2003 -> Наталья | Q72: =sales_data!F2003 -> Краснодар | R72: =sales_data!G2003 -> Южный | S72: =sales_data!H2003 -> Принтеры | ... Z72: =sales_data!O2003 -> В пути
L73: =sales_data!A2036 -> 2748 | M73: =sales_data!B2036 -> 45939 | N73: =sales_data!C2036 -> 9 | O73: =sales_data!D2036 -> Октябрь | P73: =sales_data!E2036 -> Анна | Q73: =sales_data!F2036 -> Москва | R73: =sales_data!G2036 -> Центральный | S73: =sales_data!H2036 -> Мониторы | ... Z73: =sales_data!O2036 -> Отменён
L74: =sales_data!A2055 -> 988 | M74: =sales_data!B2055 -> 45736 | N74: =sales_data!C2055 -> 20 | O74: =sales_data!D2055 -> Март | P74: =sales_data!E2055 -> Анна | Q74: =sales_data!F2055 -> Санкт-Петербург | R74: =sales_data!G2055 -> Северо-Западный | S74: =sales_data!H2055 -> Принтеры | ... Z74: =sales_data!O2055 -> Отменён
L75: =sales_data!A2090 -> 52 | M75: =sales_data!B2090 -> 45800 | N75: =sales_data!C2090 -> 23 | O75: =sales_data!D2090 -> Май | P75: =sales_data!E2090 -> Владимир | Q75: =sales_data!F2090 -> Санкт-Петербург | R75: =sales_data!G2090 -> Северо-Западный | S75: =sales_data!H2090 -> Периферия | ... Z75: =sales_data!O2090 -> Доставлен
L76: =sales_data!A2092 -> 375 | M76: =sales_data!B2092 -> 45708 | N76: =sales_data!C2092 -> 20 | O76: =sales_data!D2092 -> Февраль | P76: =sales_data!E2092 -> Татьяна | Q76: =sales_data!F2092 -> Красноярск | R76: =sales_data!G2092 -> Сибирский | S76: =sales_data!H2092 -> Принтеры | ... Z76: =sales_data!O2092 -> В пути
L77: =sales_data!A2129 -> 678 | M77: =sales_data!B2129 -> 45824 | N77: =sales_data!C2129 -> 16 | O77: =sales_data!D2129 -> Июнь | P77: =sales_data!E2129 -> Владимир | Q77: =sales_data!F2129 -> Краснодар | R77: =sales_data!G2129 -> Южный | S77: =sales_data!H2129 -> Принтеры | ... Z77: =sales_data!O2129 -> Отменён
L78: =sales_data!A2204 -> 4013 | M78: =sales_data!B2204 -> 45841 | N78: =sales_data!C2204 -> 3 | O78: =sales_data!D2204 -> Июль | P78: =sales_data!E2204 -> Павел | Q78: =sales_data!F2204 -> Санкт-Петербург | R78: =sales_data!G2204 -> Северо-Западный | S78: =sales_data!H2204 -> Принтеры | ... Z78: =sales_data!O2204 -> В пути
L79: =sales_data!A2205 -> 4071 | M79: =sales_data!B2205 -> 45795 | N79: =sales_data!C2205 -> 18 | O79: =sales_data!D2205 -> Май | P79: =sales_data!E2205 -> Анна | Q79: =sales_data!F2205 -> Новосибирск | R79: =sales_data!G2205 -> Сибирский | S79: =sales_data!H2205 -> Мониторы | ... Z79: =sales_data!O2205 -> Доставлен
L80: =sales_data!A2224 -> 213 | M80: =sales_data!B2224 -> 45831 | N80: =sales_data!C2224 -> 23 | O80: =sales_data!D2224 -> Июнь | P80: =sales_data!E2224 -> Владимир | Q80: =sales_data!F2224 -> Ростов-на-Дону | R80: =sales_data!G2224 -> Южный | S80: =sales_data!H2224 -> Мониторы | ... Z80: =sales_data!O2224 -> Доставлен
L81: =sales_data!A2243 -> 3088 | M81: =sales_data!B2243 -> 45727 | N81: =sales_data!C2243 -> 11 | O81: =sales_data!D2243 -> Март | P81: =sales_data!E2243 -> Светлана | Q81: =sales_data!F2243 -> Уфа | R81: =sales_data!G2243 -> Приволжский | S81: =sales_data!H2243 -> Мониторы | ... Z81: =sales_data!O2243 -> Доставлен
L82: =sales_data!A2248 -> 271 | M82: =sales_data!B2248 -> 45991 | N82: =sales_data!C2248 -> 30 | O82: =sales_data!D2248 -> Ноябрь | P82: =sales_data!E2248 -> Дмитрий | Q82: =sales_data!F2248 -> Красноярск | R82: =sales_data!G2248 -> Сибирский | S82: =sales_data!H2248 -> Периферия | ... Z82: =sales_data!O2248 -> Доставлен
L83: =sales_data!A2263 -> 4795 | M83: =sales_data!B2263 -> 45678 | N83: =sales_data!C2263 -> 21 | O83: =sales_data!D2263 -> Январь | P83: =sales_data!E2263 -> Владимир | Q83: =sales_data!F2263 -> Челябинск | R83: =sales_data!G2263 -> Уральский | S83: =sales_data!H2263 -> Принтеры | ... Z83: =sales_data!O2263 -> Отменён
L84: =sales_data!A2386 -> 103 | M84: =sales_data!B2386 -> 45959 | N84: =sales_data!C2386 -> 29 | O84: =sales_data!D2386 -> Октябрь | P84: =sales_data!E2386 -> Татьяна | Q84: =sales_data!F2386 -> Красноярск | R84: =sales_data!G2386 -> Сибирский | S84: =sales_data!H2386 -> Мониторы | ... Z84: =sales_data!O2386 -> Отменён
L85: =sales_data!A2448 -> 4429 | M85: =sales_data!B2448 -> 45823 | N85: =sales_data!C2448 -> 15 | O85: =sales_data!D2448 -> Июнь | P85: =sales_data!E2448 -> Дмитрий | Q85: =sales_data!F2448 -> Уфа | R85: =sales_data!G2448 -> Приволжский | S85: =sales_data!H2448 -> Мониторы | ... Z85: =sales_data!O2448 -> Отменён
L86: =sales_data!A2451 -> 351 | M86: =sales_data!B2451 -> 45944 | N86: =sales_data!C2451 -> 14 | O86: =sales_data!D2451 -> Октябрь | P86: =sales_data!E2451 -> Ольга | Q86: =sales_data!F2451 -> Челябинск | R86: =sales_data!G2451 -> Уральский | S86: =sales_data!H2451 -> Мониторы | ... Z86: =sales_data!O2451 -> В пути
L87: =sales_data!A2503 -> 1297 | M87: =sales_data!B2503 -> 46020 | N87: =sales_data!C2503 -> 29 | O87: =sales_data!D2503 -> Декабрь | P87: =sales_data!E2503 -> Алексей | Q87: =sales_data!F2503 -> Самара | R87: =sales_data!G2503 -> Приволжский | S87: =sales_data!H2503 -> Периферия | ... Z87: =sales_data!O2503 -> Отменён
L88: =sales_data!A2539 -> 4638 | M88: =sales_data!B2539 -> 45917 | N88: =sales_data!C2539 -> 17 | O88: =sales_data!D2539 -> Сентябрь | P88: =sales_data!E2539 -> Наталья | Q88: =sales_data!F2539 -> Уфа | R88: =sales_data!G2539 -> Приволжский | S88: =sales_data!H2539 -> Мониторы | ... Z88: =sales_data!O2539 -> В пути
L89: =sales_data!A2546 -> 1185 | M89: =sales_data!B2546 -> 45855 | N89: =sales_data!C2546 -> 17 | O89: =sales_data!D2546 -> Июль | P89: =sales_data!E2546 -> Ксения | Q89: =sales_data!F2546 -> Омск | R89: =sales_data!G2546 -> Сибирский | S89: =sales_data!H2546 -> Мониторы | ... Z89: =sales_data!O2546 -> Отменён
L90: =sales_data!A2548 -> 2207 | M90: =sales_data!B2548 -> 45810 | N90: =sales_data!C2548 -> 2 | O90: =sales_data!D2548 -> Июнь | P90: =sales_data!E2548 -> Светлана | Q90: =sales_data!F2548 -> Москва | R90: =sales_data!G2548 -> Центральный | S90: =sales_data!H2548 -> Мониторы | ... Z90: =sales_data!O2548 -> Доставлен
L91: =sales_data!A2572 -> 4179 | M91: =sales_data!B2572 -> 45889 | N91: =sales_data!C2572 -> 20 | O91: =sales_data!D2572 -> Август | P91: =sales_data!E2572 -> Ольга | Q91: =sales_data!F2572 -> Омск | R91: =sales_data!G2572 -> Сибирский | S91: =sales_data!H2572 -> Мониторы | ... Z91: =sales_data!O2572 -> В пути
L92: =sales_data!A2585 -> 3965 | M92: =sales_data!B2585 -> 45886 | N92: =sales_data!C2585 -> 17 | O92: =sales_data!D2585 -> Август | P92: =sales_data!E2585 -> Сергей | Q92: =sales_data!F2585 -> Казань | R92: =sales_data!G2585 -> Приволжский | S92: =sales_data!H2585 -> Мониторы | ... Z92: =sales_data!O2585 -> В пути
L93: =sales_data!A2687 -> 1050 | M93: =sales_data!B2687 -> 45814 | N93: =sales_data!C2687 -> 6 | O93: =sales_data!D2687 -> Июнь | P93: =sales_data!E2687 -> Ксения | Q93: =sales_data!F2687 -> Екатеринбург | R93: =sales_data!G2687 -> Уральский | S93: =sales_data!H2687 -> Мониторы | ... Z93: =sales_data!O2687 -> Отменён
L94: =sales_data!A2706 -> 4184 | M94: =sales_data!B2706 -> 45940 | N94: =sales_data!C2706 -> 10 | O94: =sales_data!D2706 -> Октябрь | P94: =sales_data!E2706 -> Борис | Q94: =sales_data!F2706 -> Нижний Новгород | R94: =sales_data!G2706 -> Приволжский | S94: =sales_data!H2706 -> Принтеры | ... Z94: =sales_data!O2706 -> В пути
L95: =sales_data!A2750 -> 649 | M95: =sales_data!B2750 -> 45683 | N95: =sales_data!C2750 -> 26 | O95: =sales_data!D2750 -> Январь | P95: =sales_data!E2750 -> Мария | Q95: =sales_data!F2750 -> Москва | R95: =sales_data!G2750 -> Центральный | S95: =sales_data!H2750 -> Мониторы | ... Z95: =sales_data!O2750 -> Отменён
L96: =sales_data!A2753 -> 2938 | M96: =sales_data!B2753 -> 45840 | N96: =sales_data!C2753 -> 2 | O96: =sales_data!D2753 -> Июль | P96: =sales_data!E2753 -> Елена | Q96: =sales_data!F2753 -> Омск | R96: =sales_data!G2753 -> Сибирский | S96: =sales_data!H2753 -> Мониторы | ... Z96: =sales_data!O2753 -> В пути
L97: =sales_data!A2805 -> 1753 | M97: =sales_data!B2805 -> 45825 | N97: =sales_data!C2805 -> 17 | O97: =sales_data!D2805 -> Июнь | P97: =sales_data!E2805 -> Владимир | Q97: =sales_data!F2805 -> Краснодар | R97: =sales_data!G2805 -> Южный | S97: =sales_data!H2805 -> Мониторы | ... Z97: =sales_data!O2805 -> В пути
L98: =sales_data!A2852 -> 3522 | M98: =sales_data!B2852 -> 45764 | N98: =sales_data!C2852 -> 17 | O98: =sales_data!D2852 -> Апрель | P98: =sales_data!E2852 -> Анна | Q98: =sales_data!F2852 -> Пермь | R98: =sales_data!G2852 -> Приволжский | S98: =sales_data!H2852 -> Мониторы | ... Z98: =sales_data!O2852 -> Доставлен
L99: =sales_data!A2863 -> 699 | M99: =sales_data!B2863 -> 45905 | N99: =sales_data!C2863 -> 5 | O99: =sales_data!D2863 -> Сентябрь | P99: =sales_data!E2863 -> Сергей | Q99: =sales_data!F2863 -> Уфа | R99: =sales_data!G2863 -> Приволжский | S99: =sales_data!H2863 -> Мониторы | ... Z99: =sales_data!O2863 -> В пути
L100: =sales_data!A2866 -> 77 | M100: =sales_data!B2866 -> 45678 | N100: =sales_data!C2866 -> 21 | O100: =sales_data!D2866 -> Январь | P100: =sales_data!E2866 -> Наталья | Q100: =sales_data!F2866 -> Москва | R100: =sales_data!G2866 -> Центральный | S100: =sales_data!H2866 -> Мониторы | ... Z100: =sales_data!O2866 -> Доставлен
L101: =sales_data!A2916 -> 820 | M101: =sales_data!B2916 -> 45981 | N101: =sales_data!C2916 -> 20 | O101: =sales_data!D2916 -> Ноябрь | P101: =sales_data!E2916 -> Павел | Q101: =sales_data!F2916 -> Уфа | R101: =sales_data!G2916 -> Приволжский | S101: =sales_data!H2916 -> Мониторы | ... Z101: =sales_data!O2916 -> Отменён
...

Sheet 4_Сортировка
A1: Шаг 4. Сортировка по price по убыванию
A3: order_id | B3: client | C3: city | D3: category | E3: product | F3: quantity | G3: price | H3: manager | I3: channel | J3: price_rank | L3: =sales_data!A2 -> order_id | M3: =sales_data!B2 -> date | N3: =sales_data!C2 -> day | O3: =sales_data!D2 -> month | P3: =sales_data!E2 -> manager | Q3: =sales_data!F2 -> city | R3: =sales_data!G2 -> region | S3: =sales_data!H2 -> category | ... Z3: =sales_data!O2 -> status
A4: 201 | B4: ООО Альфа | C4: Москва | D4: Ноутбуки | E4: Notebook Air | F4: 2 | G4: 55000 | H4: Анна | I4: Онлайн | J4: =RANK(G4,$G$4:$G$12,0)+COUNTIF($G$4:G4,G4)-1 -> 2 | L4: =sales_data!A3 -> 85 | M4: =sales_data!B3 -> 45881 | N4: =sales_data!C3 -> 12 | O4: =sales_data!D3 -> Август | P4: =sales_data!E3 -> Владимир | Q4: =sales_data!F3 -> Уфа | R4: =sales_data!G3 -> Приволжский | S4: =sales_data!H3 -> Аксессуары | ... Z4: =sales_data!O3 -> В пути
A5: 202 | B5: ООО Бета | C5: Санкт-Петербург | D5: Мониторы | E5: Monitor 27 | F5: 1 | G5: 23000 | H5: Борис | I5: Офлайн | J5: =RANK(G5,$G$4:$G$12,0)+COUNTIF($G$4:G5,G5)-1 -> 6 | L5: =sales_data!A4 -> 225 | M5: =sales_data!B4 -> 45697 | N5: =sales_data!C4 -> 9 | O5: =sales_data!D4 -> Февраль | P5: =sales_data!E4 -> Сергей | Q5: =sales_data!F4 -> Казань | R5: =sales_data!G4 -> Приволжский | S5: =sales_data!H4 -> Аксессуары | ... Z5: =sales_data!O4 -> Доставлен
A6: 203 | B6: ИП Гамма | C6: Москва | D6: Ноутбуки | E6: Notebook Pro | F6: 3 | G6: 72000 | H6: Анна | I6: Онлайн | J6: =RANK(G6,$G$4:$G$12,0)+COUNTIF($G$4:G6,G6)-1 -> 1 | L6: =sales_data!A5 -> 332 | M6: =sales_data!B5 -> 45941 | N6: =sales_data!C5 -> 11 | O6: =sales_data!D5 -> Октябрь | P6: =sales_data!E5 -> Борис | Q6: =sales_data!F5 -> Омск | R6: =sales_data!G5 -> Сибирский | S6: =sales_data!H5 -> Аксессуары | ... Z6: =sales_data!O5 -> В пути
A7: 204 | B7: ООО Дельта | C7: Казань | D7: Периферия | E7: Mouse Pro | F7: 5 | G7: 2500 | H7: Виктор | I7: Маркетплейс | J7: =RANK(G7,$G$4:$G$12,0)+COUNTIF($G$4:G7,G7)-1 -> 9 | L7: =sales_data!A6 -> 430 | M7: =sales_data!B6 -> 45746 | N7: =sales_data!C6 -> 30 | O7: =sales_data!D6 -> Март | P7: =sales_data!E6 -> Светлана | Q7: =sales_data!F6 -> Новосибирск | R7: =sales_data!G6 -> Сибирский | S7: =sales_data!H6 -> Аксессуары | ... Z7: =sales_data!O6 -> Отменён
A8: 205 | B8: ООО Эпсилон | C8: Москва | D8: Мониторы | E8: Monitor 24 | F8: 2 | G8: 18000 | H8: Анна | I8: Онлайн | J8: =RANK(G8,$G$4:$G$12,0)+COUNTIF($G$4:G8,G8)-1 -> 7 | L8: =sales_data!A7 -> 459 | M8: =sales_data!B7 -> 45856 | N8: =sales_data!C7 -> 18 | O8: =sales_data!D7 -> Июль | P8: =sales_data!E7 -> Мария | Q8: =sales_data!F7 -> Нижний Новгород | R8: =sales_data!G7 -> Приволжский | S8: =sales_data!H7 -> Аксессуары | ... Z8: =sales_data!O7 -> Доставлен
A9: 206 | B9: ИП Жасмин | C9: Екатеринбург | D9: Ноутбуки | E9: Notebook Lite | F9: 1 | G9: 49000 | H9: Борис | I9: Офлайн | J9: =RANK(G9,$G$4:$G$12,0)+COUNTIF($G$4:G9,G9)-1 -> 4 | L9: =sales_data!A8 -> 570 | M9: =sales_data!B8 -> 45766 | N9: =sales_data!C8 -> 19 | O9: =sales_data!D8 -> Апрель | P9: =sales_data!E8 -> Ксения | Q9: =sales_data!F8 -> Москва | R9: =sales_data!G8 -> Центральный | S9: =sales_data!H8 -> Аксессуары | ... Z9: =sales_data!O8 -> В пути
A10: 207 | B10: ООО Зета | C10: Москва | D10: Периферия | E10: Keyboard X | F10: 4 | G10: 4000 | H10: Виктор | I10: Онлайн | J10: =RANK(G10,$G$4:$G$12,0)+COUNTIF($G$4:G10,G10)-1 -> 8 | L10: =sales_data!A9 -> 639 | M10: =sales_data!B9 -> 45901 | N10: =sales_data!C9 -> 1 | O10: =sales_data!D9 -> Сентябрь | P10: =sales_data!E9 -> Павел | Q10: =sales_data!F9 -> Пермь | R10: =sales_data!G9 -> Приволжский | S10: =sales_data!H9 -> Аксессуары | ... Z10: =sales_data!O9 -> Отменён
A11: 208 | B11: ООО Ита | C11: Новосибирск | D11: Ноутбуки | E11: Notebook Air | F11: 2 | G11: 55000 | H11: Анна | I11: Маркетплейс | J11: =RANK(G11,$G$4:$G$12,0)+COUNTIF($G$4:G11,G11)-1 -> 3 | L11: =sales_data!A10 -> 665 | M11: =sales_data!B10 -> 45809 | N11: =sales_data!C10 -> 1 | O11: =sales_data!D10 -> Июнь | P11: =sales_data!E10 -> Владимир | Q11: =sales_data!F10 -> Екатеринбург | R11: =sales_data!G10 -> Уральский | S11: =sales_data!H10 -> Аксессуары | ... Z11: =sales_data!O10 -> Отменён
A12: 209 | B12: ООО Каппа | C12: Москва | D12: Ноутбуки | E12: Notebook Start | F12: 1 | G12: 43000 | H12: Борис | I12: Офлайн | J12: =RANK(G12,$G$4:$G$12,0)+COUNTIF($G$4:G12,G12)-1 -> 5 | L12: =sales_data!A11 -> 746 | M12: =sales_data!B11 -> 45979 | N12: =sales_data!C11 -> 18 | O12: =sales_data!D11 -> Ноябрь | P12: =sales_data!E11 -> Павел | Q12: =sales_data!F11 -> Воронеж | R12: =sales_data!G11 -> Центральный | S12: =sales_data!H11 -> Аксессуары | ... Z12: =sales_data!O11 -> Отменён
L13: =sales_data!A12 -> 1035 | M13: =sales_data!B12 -> 45812 | N13: =sales_data!C12 -> 4 | O13: =sales_data!D12 -> Июнь | P13: =sales_data!E12 -> Борис | Q13: =sales_data!F12 -> Москва | R13: =sales_data!G12 -> Центральный | S13: =sales_data!H12 -> Аксессуары | ... Z13: =sales_data!O12 -> Доставлен
L14: =sales_data!A13 -> 1562 | M14: =sales_data!B13 -> 45696 | N14: =sales_data!C13 -> 8 | O14: =sales_data!D13 -> Февраль | P14: =sales_data!E13 -> Игорь | Q14: =sales_data!F13 -> Казань | R14: =sales_data!G13 -> Приволжский | S14: =sales_data!H13 -> Аксессуары | ... Z14: =sales_data!O13 -> Отменён
L15: =sales_data!A14 -> 1720 | M15: =sales_data!B14 -> 45786 | N15: =sales_data!C14 -> 9 | O15: =sales_data!D14 -> Май | P15: =sales_data!E14 -> Наталья | Q15: =sales_data!F14 -> Нижний Новгород | R15: =sales_data!G14 -> Приволжский | S15: =sales_data!H14 -> Аксессуары | ... Z15: =sales_data!O14 -> В пути
L16: =sales_data!A15 -> 1722 | M16: =sales_data!B15 -> 45798 | N16: =sales_data!C15 -> 21 | O16: =sales_data!D15 -> Май | P16: =sales_data!E15 -> Татьяна | Q16: =sales_data!F15 -> Самара | R16: =sales_data!G15 -> Приволжский | S16: =sales_data!H15 -> Аксессуары | ... Z16: =sales_data!O15 -> В пути
L17: =sales_data!A16 -> 1736 | M17: =sales_data!B16 -> 45985 | N17: =sales_data!C16 -> 24 | O17: =sales_data!D16 -> Ноябрь | P17: =sales_data!E16 -> Игорь | Q17: =sales_data!F16 -> Екатеринбург | R17: =sales_data!G16 -> Уральский | S17: =sales_data!H16 -> Аксессуары | ... Z17: =sales_data!O16 -> В пути
L18: =sales_data!A17 -> 1872 | M18: =sales_data!B17 -> 45779 | N18: =sales_data!C17 -> 2 | O18: =sales_data!D17 -> Май | P18: =sales_data!E17 -> Татьяна | Q18: =sales_data!F17 -> Челябинск | R18: =sales_data!G17 -> Уральский | S18: =sales_data!H17 -> Аксессуары | ... Z18: =sales_data!O17 -> В пути
L19: =sales_data!A18 -> 1950 | M19: =sales_data!B18 -> 45736 | N19: =sales_data!C18 -> 20 | O19: =sales_data!D18 -> Март | P19: =sales_data!E18 -> Владимир | Q19: =sales_data!F18 -> Казань | R19: =sales_data!G18 -> Приволжский | S19: =sales_data!H18 -> Аксессуары | ... Z19: =sales_data!O18 -> Доставлен
L20: =sales_data!A19 -> 2086 | M20: =sales_data!B19 -> 45742 | N20: =sales_data!C19 -> 26 | O20: =sales_data!D19 -> Март | P20: =sales_data!E19 -> Игорь | Q20: =sales_data!F19 -> Казань | R20: =sales_data!G19 -> Приволжский | S20: =sales_data!H19 -> Аксессуары | ... Z20: =sales_data!O19 -> Доставлен
L21: =sales_data!A20 -> 2264 | M21: =sales_data!B20 -> 45911 | N21: =sales_data!C20 -> 11 | O21: =sales_data!D20 -> Сентябрь | P21: =sales_data!E20 -> Павел | Q21: =sales_data!F20 -> Челябинск | R21: =sales_data!G20 -> Уральский | S21: =sales_data!H20 -> Аксессуары | ... Z21: =sales_data!O20 -> Отменён
L22: =sales_data!A21 -> 2345 | M22: =sales_data!B21 -> 45934 | N22: =sales_data!C21 -> 4 | O22: =sales_data!D21 -> Октябрь | P22: =sales_data!E21 -> Дмитрий | Q22: =sales_data!F21 -> Краснодар | R22: =sales_data!G21 -> Южный | S22: =sales_data!H21 -> Аксессуары | ... Z22: =sales_data!O21 -> В пути
L23: =sales_data!A22 -> 2401 | M23: =sales_data!B22 -> 45969 | N23: =sales_data!C22 -> 8 | O23: =sales_data!D22 -> Ноябрь | P23: =sales_data!E22 -> Мария | Q23: =sales_data!F22 -> Москва | R23: =sales_data!G22 -> Центральный | S23: =sales_data!H22 -> Аксессуары | ... Z23: =sales_data!O22 -> Отменён
L24: =sales_data!A23 -> 2552 | M24: =sales_data!B23 -> 45973 | N24: =sales_data!C23 -> 12 | O24: =sales_data!D23 -> Ноябрь | P24: =sales_data!E23 -> Ксения | Q24: =sales_data!F23 -> Казань | R24: =sales_data!G23 -> Приволжский | S24: =sales_data!H23 -> Аксессуары | ... Z24: =sales_data!O23 -> Отменён
L25: =sales_data!A24 -> 2711 | M25: =sales_data!B24 -> 45964 | N25: =sales_data!C24 -> 3 | O25: =sales_data!D24 -> Ноябрь | P25: =sales_data!E24 -> Анна | Q25: =sales_data!F24 -> Красноярск | R25: =sales_data!G24 -> Сибирский | S25: =sales_data!H24 -> Аксессуары | ... Z25: =sales_data!O24 -> Отменён

Sheet 5_Новые_столбцы
A1: Шаг 5. Создаём столбец revenue и ищем крупные заказы
A3: order_id | B3: client | C3: city | D3: category | E3: product | F3: quantity | G3: price | H3: manager | I3: channel | J3: revenue | K3: big_order | M3: Топ-5 по revenue
A4: 201 | B4: ООО Альфа | C4: Москва | D4: Ноутбуки | E4: Notebook Air | F4: 2 | G4: 55000 | H4: Анна | I4: Онлайн | J4: =F4*G4 -> 110000 | K4: =IF(J4>=100000,"Крупный заказ","Обычный") -> Крупный заказ | M4: order_id | N4: date | O4: day | P4: month | Q4: manager | R4: city | S4: region | T4: category | U4: product | V4: client_type | W4: quantity | X4: price_per_unit | Y4: revenue | Z4: channel | AA4: status
A5: 202 | B5: ООО Бета | C5: Санкт-Петербург | D5: Мониторы | E5: Monitor 27 | F5: 1 | G5: 23000 | H5: Борис | I5: Офлайн | J5: =F5*G5 -> 23000 | K5: =IF(J5>=100000,"Крупный заказ","Обычный") -> Обычный | M5: =sales_data!A2 -> order_id | N5: =sales_data!B2 -> date | O5: =sales_data!C2 -> day | P5: =sales_data!D2 -> month | Q5: =sales_data!E2 -> manager | R5: =sales_data!F2 -> city | S5: =sales_data!G2 -> region | T5: =sales_data!H2 -> category | ... AA5: =sales_data!O2 -> status
A6: 203 | B6: ИП Гамма | C6: Москва | D6: Ноутбуки | E6: Notebook Pro | F6: 3 | G6: 72000 | H6: Анна | I6: Онлайн | J6: =F6*G6 -> 216000 | K6: =IF(J6>=100000,"Крупный заказ","Обычный") -> Крупный заказ | M6: =sales_data!A4892 -> 2981 | N6: =sales_data!B4892 -> 45991 | O6: =sales_data!C4892 -> 30 | P6: =sales_data!D4892 -> Ноябрь | Q6: =sales_data!E4892 -> Павел | R6: =sales_data!F4892 -> Самара | S6: =sales_data!G4892 -> Приволжский | T6: =sales_data!H4892 -> Серверы | ... AA6: =sales_data!O4892 -> Доставлен
A7: 204 | B7: ООО Дельта | C7: Казань | D7: Периферия | E7: Mouse Pro | F7: 5 | G7: 2500 | H7: Виктор | I7: Маркетплейс | J7: =F7*G7 -> 12500 | K7: =IF(J7>=100000,"Крупный заказ","Обычный") -> Обычный | M7: =sales_data!A4912 -> 2930 | N7: =sales_data!B4912 -> 45820 | O7: =sales_data!C4912 -> 12 | P7: =sales_data!D4912 -> Июнь | Q7: =sales_data!E4912 -> Наталья | R7: =sales_data!F4912 -> Санкт-Петербург | S7: =sales_data!G4912 -> Северо-Западный | T7: =sales_data!H4912 -> Серверы | ... AA7: =sales_data!O4912 -> В пути
A8: 205 | B8: ООО Эпсилон | C8: Москва | D8: Мониторы | E8: Monitor 24 | F8: 2 | G8: 18000 | H8: Анна | I8: Онлайн | J8: =F8*G8 -> 36000 | K8: =IF(J8>=100000,"Крупный заказ","Обычный") -> Обычный | M8: =sales_data!A4915 -> 1711 | N8: =sales_data!B4915 -> 45926 | O8: =sales_data!C4915 -> 26 | P8: =sales_data!D4915 -> Сентябрь | Q8: =sales_data!E4915 -> Ксения | R8: =sales_data!F4915 -> Новосибирск | S8: =sales_data!G4915 -> Сибирский | T8: =sales_data!H4915 -> Серверы | ... AA8: =sales_data!O4915 -> В пути
A9: 206 | B9: ИП Жасмин | C9: Екатеринбург | D9: Ноутбуки | E9: Notebook Lite | F9: 1 | G9: 49000 | H9: Борис | I9: Офлайн | J9: =F9*G9 -> 49000 | K9: =IF(J9>=100000,"Крупный заказ","Обычный") -> Обычный | M9: =sales_data!A4920 -> 1388 | N9: =sales_data!B4920 -> 45853 | O9: =sales_data!C4920 -> 15 | P9: =sales_data!D4920 -> Июль | Q9: =sales_data!E4920 -> Анна | R9: =sales_data!F4920 -> Уфа | S9: =sales_data!G4920 -> Приволжский | T9: =sales_data!H4920 -> Серверы | ... AA9: =sales_data!O4920 -> Доставлен
A10: 207 | B10: ООО Зета | C10: Москва | D10: Периферия | E10: Keyboard X | F10: 4 | G10: 4000 | H10: Виктор | I10: Онлайн | J10: =F10*G10 -> 16000 | K10: =IF(J10>=100000,"Крупный заказ","Обычный") -> Обычный | M10: =sales_data!A4931 -> 2176 | N10: =sales_data!B4931 -> 45718 | O10: =sales_data!C4931 -> 2 | P10: =sales_data!D4931 -> Март | Q10: =sales_data!E4931 -> Алексей | R10: =sales_data!F4931 -> Воронеж | S10: =sales_data!G4931 -> Центральный | T10: =sales_data!H4931 -> Серверы | ... AA10: =sales_data!O4931 -> Отменён
A11: 208 | B11: ООО Ита | C11: Новосибирск | D11: Ноутбуки | E11: Notebook Air | F11: 2 | G11: 55000 | H11: Анна | I11: Маркетплейс | J11: =F11*G11 -> 110000 | K11: =IF(J11>=100000,"Крупный заказ","Обычный") -> Крупный заказ | M11: Количество крупных заказов | N11: 5
A12: 209 | B12: ООО Каппа | C12: Москва | D12: Ноутбуки | E12: Notebook Start | F12: 1 | G12: 43000 | H12: Борис | I12: Офлайн | J12: =F12*G12 -> 43000 | K12: =IF(J12>=100000,"Крупный заказ","Обычный") -> Обычный

Sheet 6_Тест
A1: Тест по занятию 8
A3: Вопрос | B3: Правильный ответ | C3: Подсказка
A4: Сколько строк в исходной таблице? | B4: 5000 | C4: Аналог df.shape[0]
A5: Сколько заказов попадает в фильтр category == "Ноутбуки"? | B5: 813 | C5: Смотрите sheet 2 или notebook cell 2
A6: Сколько заказов попадает в фильтр city == "Москва" и channel == "Онлайн"? | B6: 156 | C6: Используйте AND в Excel и & в pandas
A7: Какая общая выручка после создания столбца revenue? | B7: 2612584200 | C7: Это сумма quantity * price
A8: Сколько крупных заказов с revenue >= 100000? | B8: 2763 | C8: Смотрите столбец big_order
