Workbook

Sheet 0_Теория
A1: Занятие 6. Загрузка данных из CSV и Excel. Первое знакомство с pandas
A3: Тема | B3: Загрузка CSV и Excel, структура DataFrame, просмотр строк и столбцов.
A4: Ключевые термины | B4: CSV, Excel, pandas, DataFrame, строки, столбцы, sheet_name.
A5: Что делает ноутбук | B5: Создаёт CSV, читает CSV и Excel, показывает head/tail, shape, columns и выбор столбцов.
A6: Как использовать | B6: Положите ноутбук и этот Excel-файл в одну папку, затем откройте файл в ячейке 2 через pd.read_excel(...).
A7: Лист для чтения | B7: data
A10: Практические шаги
A11: 1. Импорт pandas и чтение CSV
A12: 2. Чтение Excel-листа data
A13: 3. Просмотр head, tail, shape, columns
A14: 4. Выбор одного и нескольких столбцов
A15: 5. Мини-задача по описанию структуры таблицы

Sheet data
A1: order_id | B1: client | C1: city | D1: category | E1: product | F1: quantity | G1: price | H1: revenue
A2: 1 | B2: ООО Альфа | C2: Москва | D2: Ноутбуки | E2: Notebook Air | F2: 2 | G2: 55000 | H2: =F2*G2 -> 110000
A3: 2 | B3: ООО Бета | C3: Казань | D3: Мониторы | E3: Монитор 24 | F3: 3 | G3: 18000 | H3: =F3*G3 -> 54000
A4: 3 | B4: ИП Гамма | C4: Уфа | D4: Периферия | E4: Мышь Pro | F4: 5 | G4: 1500 | H4: =F4*G4 -> 7500
A5: 4 | B5: ООО Дельта | C5: Самара | D5: Ноутбуки | E5: Notebook Pro | F5: 1 | G5: 87000 | H5: =F5*G5 -> 87000
A6: 5 | B6: ИП Омега | C6: Омск | D6: Периферия | E6: Клавиатура | F6: 4 | G6: 3200 | H6: =F6*G6 -> 12800
A7: 6 | B7: ООО Вектор | C7: Томск | D7: Мониторы | E7: Монитор 27 | F7: 2 | G7: 24000 | H7: =F7*G7 -> 48000

Sheet 1_CSV
A1: Как выглядит CSV
A3: В ноутбуке эти строки сохраняются в файл lesson_06_sales_data.csv
A5: Строка CSV
A6: order_id,client,city,category,product,quantity,price,revenue
A7: 1,ООО Альфа,Москва,Ноутбуки,Notebook Air,2,55000,110000
A8: 2,ООО Бета,Казань,Мониторы,Монитор 24,3,18000,54000
A9: 3,ИП Гамма,Уфа,Периферия,Мышь Pro,5,1500,7500
A10: 4,ООО Дельта,Самара,Ноутбуки,Notebook Pro,1,87000,87000
A11: 5,ИП Омега,Омск,Периферия,Клавиатура,4,3200,12800
A12: 6,ООО Вектор,Томск,Мониторы,Монитор 27,2,24000,48000

Sheet 2_Excel
A1: Чтение Excel-листа data
A3: Имя файла | B3: lesson_06_pandas_intro.xlsx
A4: Лист для чтения | B4: data
A5: Команда в pandas | B5: pd.read_excel("lesson_06_pandas_intro.xlsx", sheet_name="data")
A6: Что получится | B6: DataFrame из 6 строк и 8 столбцов
A9: Первые 3 строки листа data
A10: =data!A1 -> order_id | B10: =data!B1 -> client | C10: =data!C1 -> city | D10: =data!D1 -> category | E10: =data!E1 -> product | F10: =data!F1 -> quantity | G10: =data!G1 -> price | H10: =data!H1 -> revenue
A11: =data!A2 -> 1 | B11: =data!B2 -> ООО Альфа | C11: =data!C2 -> Москва | D11: =data!D2 -> Ноутбуки | E11: =data!E2 -> Notebook Air | F11: =data!F2 -> 2 | G11: =data!G2 -> 55000 | H11: =data!H2 -> 110000
A12: =data!A3 -> 2 | B12: =data!B3 -> ООО Бета | C12: =data!C3 -> Казань | D12: =data!D3 -> Мониторы | E12: =data!E3 -> Монитор 24 | F12: =data!F3 -> 3 | G12: =data!G3 -> 18000 | H12: =data!H3 -> 54000
A13: =data!A4 -> 3 | B13: =data!B4 -> ИП Гамма | C13: =data!C4 -> Уфа | D13: =data!D4 -> Периферия | E13: =data!E4 -> Мышь Pro | F13: =data!F4 -> 5 | G13: =data!G4 -> 1500 | H13: =data!H4 -> 7500

Sheet 3_Просмотр
A1: Просмотр структуры таблицы
A3: Показатель | B3: Значение | D3: Аналог df.head()
A4: Количество строк | B4: =COUNTA(data!A:A)-1 -> 6 | D4: =data!A1 -> order_id | E4: =data!B1 -> client | F4: =data!C1 -> city | G4: =data!D1 -> category | H4: =data!E1 -> product | I4: =data!F1 -> quantity | J4: =data!G1 -> price | K4: =data!H1 -> revenue
A5: Количество столбцов | B5: =COUNTA(data!1:1) -> 8 | D5: =data!A2 -> 1 | E5: =data!B2 -> ООО Альфа | F5: =data!C2 -> Москва | G5: =data!D2 -> Ноутбуки | H5: =data!E2 -> Notebook Air | I5: =data!F2 -> 2 | J5: =data!G2 -> 55000 | K5: =data!H2 -> 110000
A6: Список столбцов | B6: order_id, client, city, category, product, quantity, price, revenue | D6: =data!A3 -> 2 | E6: =data!B3 -> ООО Бета | F6: =data!C3 -> Казань | G6: =data!D3 -> Мониторы | H6: =data!E3 -> Монитор 24 | I6: =data!F3 -> 3 | J6: =data!G3 -> 18000 | K6: =data!H3 -> 54000
A7: Аналог команды | B7: df.head(), df.tail(3), df.shape, list(df.columns) | D7: =data!A4 -> 3 | E7: =data!B4 -> ИП Гамма | F7: =data!C4 -> Уфа | G7: =data!D4 -> Периферия | H7: =data!E4 -> Мышь Pro | I7: =data!F4 -> 5 | J7: =data!G4 -> 1500 | K7: =data!H4 -> 7500
D8: =data!A5 -> 4 | E8: =data!B5 -> ООО Дельта | F8: =data!C5 -> Самара | G8: =data!D5 -> Ноутбуки | H8: =data!E5 -> Notebook Pro | I8: =data!F5 -> 1 | J8: =data!G5 -> 87000 | K8: =data!H5 -> 87000
D9: =data!A6 -> 5 | E9: =data!B6 -> ИП Омега | F9: =data!C6 -> Омск | G9: =data!D6 -> Периферия | H9: =data!E6 -> Клавиатура | I9: =data!F6 -> 4 | J9: =data!G6 -> 3200 | K9: =data!H6 -> 12800
D12: Аналог df.tail(3)
D13: =data!A1 -> order_id | E13: =data!B1 -> client | F13: =data!C1 -> city | G13: =data!D1 -> category | H13: =data!E1 -> product | I13: =data!F1 -> quantity | J13: =data!G1 -> price | K13: =data!H1 -> revenue
D14: =data!A5 -> 4 | E14: =data!B5 -> ООО Дельта | F14: =data!C5 -> Самара | G14: =data!D5 -> Ноутбуки | H14: =data!E5 -> Notebook Pro | I14: =data!F5 -> 1 | J14: =data!G5 -> 87000 | K14: =data!H5 -> 87000
D15: =data!A6 -> 5 | E15: =data!B6 -> ИП Омега | F15: =data!C6 -> Омск | G15: =data!D6 -> Периферия | H15: =data!E6 -> Клавиатура | I15: =data!F6 -> 4 | J15: =data!G6 -> 3200 | K15: =data!H6 -> 12800
D16: =data!A7 -> 6 | E16: =data!B7 -> ООО Вектор | F16: =data!C7 -> Томск | G16: =data!D7 -> Мониторы | H16: =data!E7 -> Монитор 27 | I16: =data!F7 -> 2 | J16: =data!G7 -> 24000 | K16: =data!H7 -> 48000

Sheet 4_Столбцы
A1: Выбор одного и нескольких столбцов
A3: Один столбец: quantity | C3: Несколько столбцов: client, product, revenue
A4: quantity | C4: client | D4: product | E4: revenue
A5: =data!F2 -> 2 | C5: =data!B2 -> ООО Альфа | D5: =data!E2 -> Notebook Air | E5: =data!H2 -> 110000
A6: =data!F3 -> 3 | C6: =data!B3 -> ООО Бета | D6: =data!E3 -> Монитор 24 | E6: =data!H3 -> 54000
A7: =data!F4 -> 5 | C7: =data!B4 -> ИП Гамма | D7: =data!E4 -> Мышь Pro | E7: =data!H4 -> 7500
A8: =data!F5 -> 1 | C8: =data!B5 -> ООО Дельта | D8: =data!E5 -> Notebook Pro | E8: =data!H5 -> 87000
A9: =data!F6 -> 4 | C9: =data!B6 -> ИП Омега | D9: =data!E6 -> Клавиатура | E9: =data!H6 -> 12800
A10: =data!F7 -> 2 | C10: =data!B7 -> ООО Вектор | D10: =data!E7 -> Монитор 27 | E10: =data!H7 -> 48000

Sheet 5_Минизадача
A1: Мини-задача: описываем структуру набора данных
A3: Что найти | B3: Ответ
A4: Количество строк | B4: =COUNTA(data!A:A)-1 -> 6
A5: Количество столбцов | B5: =COUNTA(data!1:1) -> 8
A6: Общая выручка | B6: =SUM(data!H2:H7) -> 319300
A8: Первые 3 товара | C8: Список столбцов
A9: product | C9: order_id
A10: =data!E2 -> Notebook Air | C10: client
A11: =data!E3 -> Монитор 24 | C11: city
A12: =data!E4 -> Мышь Pro | C12: category
C13: product
C14: quantity
C15: price
C16: revenue

Sheet 6_Тест
A1: Тест по занятию
A3: Вопрос | B3: Правильный ответ | C3: Подсказка
A4: Сколько строк в таблице? | B4: =COUNTA(data!A:A)-1 -> 6 | C4: Аналог df.shape[0]
A5: Сколько столбцов в таблице? | B5: =COUNTA(data!1:1) -> 8 | C5: Аналог df.shape[1]
A6: Как называется лист для чтения? | B6: data | C6: sheet_name="data"
A7: Какая сумма в столбце revenue? | B7: =SUM(data!H2:H7) -> 319300 | C7: df["revenue"].sum()
A9: Проверка
A10: Формула в pandas | B10: df[["client", "product", "revenue"]]
